{"value":[{"FiscalYear":{"Title":"2016"},"Donor":{"Title":"Pacific Life Foundation"},"DonorType":{"Title":"Corporate"},"Program":{"Title":"Policy + Governance"},"Duration":{"Title":"1"},"FundingStatus":{"Id":4,"Title":"Booked"},"Author":{"Title":"Ashleigh McGovern"},"Editor":{"Title":"Ashleigh McGovern"},"Id":1,"Project":"Flexible","TotalCommitment":1000000.0,"ProgramCommitment":1000000.0,"FieldSiteCommitment":0.0,"Notes":"Ocean Health Index","ID":1,"Modified":"2016-11-30T18:12:02Z","Created":"2016-06-25T20:38:35Z"},{"FiscalYear":{"Title":"2014"},"Donor":{"Title":"MacArthur Foundation (Chris Holtz, Kate Barnes)"},"DonorType":{"Title":"Foundation"},"Program":{"Title":"Connected Oceans"},"FieldSite":{"Title":"Abrolhos Seascape"},"FundingStatus":{"Id":4,"Title":"Booked"},"Author":{"Title":"Ashleigh McGovern"},"Editor":{"Title":"Ashleigh McGovern"},"Id":2,"Project":"Sustainable Community-based Management of the Ambodivahibe Marine Protected Area","TotalCommitment":150000.0,"ProgramCommitment":0.0,"FieldSiteCommitment":150000.0,"Notes":null,"ID":2,"Modified":"2016-07-06T22:06:54Z","Created":"2016-06-25T20:38:35Z"},{"FiscalYear":{"Title":"2015"},"Donor":{"Title":"Pacific Life Foundation"},"DonorType":{"Title":"Corporate"},"Program":{"Title":"Policy + Governance"},"Duration":{"Title":"1"},"FundingStatus":{"Id":4,"Title":"Booked"},"Author":{"Title":"Ashleigh McGovern"},"Editor":{"Title":"Ashleigh McGovern"},"Id":3,"Project":"OHI Flexible","TotalCommitment":1000000.0,"ProgramCommitment":1000000.0,"FieldSiteCommitment":0.0,"Notes":"Ocean Health Index","ID":3,"Modified":"2016-11-30T18:11:53Z","Created":"2016-06-25T20:38:35Z"},{"FiscalYear":{"Title":"2015"},"Donor":{"Title":"Stena (Dan Sten Olssen, Claes Burglund & Kenneth MacLeod)"},"DonorType":{"Title":"Corporate"},"Program":{"Title":"Policy + Governance"},"Duration":{"Title":"1"},"FundingStatus":{"Id":4,"Title":"Booked"},"Author":{"Title":"Ashleigh McGovern"},"Editor":{"Title":"Ashleigh McGovern"},"Id":4,"Project":"Ocean Health Index","TotalCommitment":1500000.0,"ProgramCommitment":1500000.0,"FieldSiteCommitment":0.0,"Notes":"Ocean Health Index","ID":4,"Modified":"2016-11-30T18:11:49Z","Created":"2016-06-25T20:38:35Z"},{"FiscalYear":{"Title":"2014"},"Donor":{"Title":"Conoco Philips"},"DonorType":{"Title":"Corporate"},"Program":{"Title":"Connected Oceans"},"FieldSite":{"Title":"Bird's Head Seascape"},"Duration":{"Title":"1"},"FundingStatus":{"Id":4,"Title":"Booked"},"Author":{"Title":"Ashleigh McGovern"},"Editor":{"Title":"Ashleigh McGovern"},"Id":5,"Project":"Anambas Natuna Seascape - RAP","TotalCommitment":347997.0,"ProgramCommitment":0.0,"FieldSiteCommitment":347997.0,"Notes":null,"ID":5,"Modified":"2016-08-09T18:35:15Z","Created":"2016-06-25T20:38:35Z"},{"FiscalYear":{"Title":"2016"},"Donor":{"Title":"Leonardo DiCaprio Foundation (Justin Winters)"},"DonorType":{"Title":"Foundation"},"Program":{"Title":"Connected Oceans"},"FieldSite":{"Title":"Bird's Head Seascape"},"Duration":{"Title":"3"},"FundingStatus":{"Id":4,"Title":"Booked"},"Author":{"Title":"Ashleigh McGovern"},"Editor":{"Title":"Ashleigh McGovern"},"Id":6,"Project":"Bird\u2019s Head and the Conserving the Reefs of Pyai Nemo and Bambu Islands Through Community Action Project","TotalCommitment":1000000.0,"ProgramCommitment":0.0,"FieldSiteCommitment":1000000.0,"Notes":null,"ID":6,"Modified":"2016-07-06T22:06:54Z","Created":"2016-06-25T20:38:35Z"},{"FiscalYear":{"Title":"2016"},"Donor":{"Title":"Walton Family Foundation"},"DonorType":{"Title":"Foundation"},"Program":{"Title":"Connected Oceans"},"FieldSite":{"Title":"Bird's Head Seascape"},"Duration":{"Title":"1"},"FundingStatus":{"Id":4,"Title":"Booked"},"Author":{"Title":"Ashleigh McGovern"},"Editor":{"Title":"Ashleigh McGovern"},"Id":7,"Project":"Conserving the Reefs of Pyai Nemo and Bambu Islands Through a Community Action Project (BHS)","TotalCommitment":30000.0,"ProgramCommitment":0.0,"FieldSiteCommitment":30000.0,"Notes":null,"ID":7,"Modified":"2016-07-06T22:06:54Z","Created":"2016-06-25T20:38:36Z"},{"FiscalYear":{"Title":"2016"},"Donor":{"Title":"MacArthur Foundation (Chris Holtz, Kate Barnes)"},"DonorType":{"Title":"Foundation"},"Program":{"Title":"Connected Oceans"},"FieldSite":{"Title":"Northern Mozambique Channel"},"Duration":{"Title":"3"},"FundingStatus":{"Id":4,"Title":"Booked"},"Author":{"Title":"Ashleigh McGovern"},"Editor":{"Title":"Ashleigh McGovern"},"Id":8,"Project":"Sustainable Community-based Management of the Ambodivahibe Marine Protected Area","TotalCommitment":400000.0,"ProgramCommitment":10000.0,"FieldSiteCommitment":390000.0,"Notes":null,"ID":8,"Modified":"2016-07-06T22:06:54Z","Created":"2016-06-25T20:38:36Z"},{"FiscalYear":{"Title":"2013"},"Donor":{"Title":"MacArthur Foundation (Chris Holtz, Kate Barnes)"},"DonorType":{"Title":"Foundation"},"Program":{"Title":"Connected Oceans"},"FieldSite":{"Title":"Bird's Head Seascape"},"FundingStatus":{"Id":4,"Title":"Booked"},"Author":{"Title":"Ashleigh McGovern"},"Editor":{"Title":"Ashleigh McGovern"},"Id":9,"Project":"Bird's Head Seascape","TotalCommitment":400000.0,"ProgramCommitment":0.0,"FieldSiteCommitment":400000.0,"Notes":null,"ID":9,"Modified":"2016-07-06T22:06:54Z","Created":"2016-06-25T20:38:36Z"},{"FiscalYear":{"Title":"2013"},"Donor":{"Title":"Walton Family Foundation"},"DonorType":{"Title":"Foundation"},"Program":{"Title":"Connected Oceans"},"FieldSite":{"Title":"Bird's Head Seascape"},"FundingStatus":{"Id":4,"Title":"Booked"},"Author":{"Title":"Ashleigh McGovern"},"Editor":{"Title":"Ashleigh McGovern"},"Id":10,"Project":"Bird's Head Seascape - M&E","TotalCommitment":468299.0,"ProgramCommitment":0.0,"FieldSiteCommitment":468299.0,"Notes":null,"ID":10,"Modified":"2016-07-06T22:06:54Z","Created":"2016-06-25T20:38:36Z"},{"FiscalYear":{"Title":"2014"},"Donor":{"Title":"Walton Family Foundation"},"DonorType":{"Title":"Foundation"},"Program":{"Title":"Connected Oceans"},"FieldSite":{"Title":"Bird's Head Seascape"},"Duration":{"Title":"3"},"FundingStatus":{"Id":4,"Title":"Booked"},"Author":{"Title":"Ashleigh McGovern"},"Editor":{"Title":"Ashleigh McGovern"},"Id":11,"Project":"Bird's Head Seascape","TotalCommitment":12990000.0,"ProgramCommitment":0.0,"FieldSiteCommitment":12990000.0,"Notes":null,"ID":11,"Modified":"2016-08-09T18:35:02Z","Created":"2016-06-25T20:38:36Z"},{"FiscalYear":{"Title":"2014"},"Donor":{"Title":"The David and Lucile Packard Foundation"},"DonorType":{"Title":"Foundation"},"Program":{"Title":"Connected Oceans"},"FieldSite":{"Title":"Bird's Head Seascape"},"FundingStatus":{"Id":4,"Title":"Booked"},"Author":{"Title":"Ashleigh McGovern"},"Editor":{"Title":"Ashleigh McGovern"},"Id":12,"Project":"Bird's Head Seascape","TotalCommitment":250000.0,"ProgramCommitment":0.0,"FieldSiteCommitment":250000.0,"Notes":null,"ID":12,"Modified":"2016-07-06T22:06:55Z","Created":"2016-06-25T20:38:36Z"},{"FiscalYear":{"Title":"2016"},"Donor":{"Title":"Nippon Foundation"},"DonorType":{"Title":"Foundation"},"Program":{"Title":"Resilient Fisheries"},"Duration":{"Title":"1"},"FundingStatus":{"Id":4,"Title":"Booked"},"Author":{"Title":"Ashleigh McGovern"},"Editor":{"Title":"Ashleigh McGovern"},"Id":13,"Project":"With US Soybean Export Council with potential co-funding from Tuner Foundation to study the sustainability of aquaculture feeds","TotalCommitment":80000.0,"ProgramCommitment":80000.0,"FieldSiteCommitment":0.0,"Notes":null,"ID":13,"Modified":"2016-07-06T22:06:55Z","Created":"2016-06-25T20:38:36Z"},{"FiscalYear":{"Title":"2013"},"Donor":{"Title":"USAID"},"DonorType":{"Title":"Public"},"Program":{"Title":"Connected Oceans"},"FieldSite":{"Title":"Bird's Head Seascape"},"FundingStatus":{"Id":4,"Title":"Booked"},"Author":{"Title":"Ashleigh McGovern"},"Editor":{"Title":"Ashleigh McGovern"},"Id":14,"Project":"Year Three MPAG program","TotalCommitment":575000.0,"ProgramCommitment":0.0,"FieldSiteCommitment":575000.0,"Notes":null,"ID":14,"Modified":"2016-08-23T16:58:34Z","Created":"2016-06-25T20:38:36Z"},{"FiscalYear":{"Title":"2016"},"Donor":{"Title":"Moore Family Foundation (Gordon Moore / Steve Moore)"},"DonorType":{"Title":"Foundation"},"Program":{"Title":"Hawaii"},"Duration":{"Title":"2"},"FundingStatus":{"Id":4,"Title":"Booked"},"Author":{"Title":"Ashleigh McGovern"},"Editor":{"Title":"Ashleigh McGovern"},"Id":15,"Project":"Flexible","TotalCommitment":150000.0,"ProgramCommitment":150000.0,"FieldSiteCommitment":0.0,"Notes":null,"ID":15,"Modified":"2016-07-06T22:06:55Z","Created":"2016-06-25T20:38:36Z"},{"FiscalYear":{"Title":"2016"},"Donor":{"Title":"Cooke Foundation"},"DonorType":{"Title":"Foundation"},"Program":{"Title":"Hawaii"},"Duration":{"Title":"1"},"FundingStatus":{"Id":4,"Title":"Booked"},"Author":{"Title":"Ashleigh McGovern"},"Editor":{"Title":"Ashleigh McGovern"},"Id":16,"Project":"Building the Sustainability of Community-based Fisheries in Milolii South Kona, Hawaii","TotalCommitment":5000.0,"ProgramCommitment":5000.0,"FieldSiteCommitment":0.0,"Notes":null,"ID":16,"Modified":"2016-07-06T22:06:55Z","Created":"2016-06-25T20:38:36Z"},{"FiscalYear":{"Title":"2016"},"Donor":{"Title":"Ulupono Initiative (Pam and Pierre Omidyar)"},"DonorType":{"Title":"Foundation"},"Program":{"Title":"Hawaii"},"Duration":{"Title":"1"},"FundingStatus":{"Id":4,"Title":"Booked"},"Author":{"Title":"Ashleigh McGovern"},"Editor":{"Title":"Ashleigh McGovern"},"Id":17,"Project":"Seafood traceability","TotalCommitment":50000.0,"ProgramCommitment":50000.0,"FieldSiteCommitment":0.0,"Notes":null,"ID":17,"Modified":"2016-07-06T22:06:55Z","Created":"2016-06-25T20:38:36Z"},{"FiscalYear":{"Title":"2013"},"Donor":{"Title":"World Bank"},"DonorType":{"Title":"Public"},"Program":{"Title":"Resilient Fisheries"},"FieldSite":{"Title":"Eastern Tropical Pacific Seascape"},"Duration":{"Title":"4"},"FundingStatus":{"Id":4,"Title":"Booked"},"Author":{"Title":"Ashleigh McGovern"},"Editor":{"Title":"Ashleigh McGovern"},"Id":18,"Project":"Areas Beyond National Jurisdiction (ABNJ)","TotalCommitment":2162637.0,"ProgramCommitment":0.0,"FieldSiteCommitment":2162637.0,"Notes":null,"ID":18,"Modified":"2016-08-09T18:34:34Z","Created":"2016-06-25T20:38:36Z"},{"FiscalYear":{"Title":"2015"},"Donor":{"Title":"Oceans 5"},"DonorType":{"Title":"Foundation"},"Program":{"Title":"Connected Oceans"},"FieldSite":{"Title":"Eastern Tropical Pacific Seascape"},"Duration":{"Title":"4"},"FundingStatus":{"Id":4,"Title":"Booked"},"Author":{"Title":"Ashleigh McGovern"},"Editor":{"Title":"Ashleigh McGovern"},"Id":19,"Project":"Eastern Tropical Pacific Seascape - Enforcement","TotalCommitment":6100000.0,"ProgramCommitment":0.0,"FieldSiteCommitment":6100000.0,"Notes":null,"ID":19,"Modified":"2016-07-06T22:06:55Z","Created":"2016-06-25T20:38:36Z"},{"FiscalYear":{"Title":"2014"},"Donor":{"Title":"Walton Family Foundation"},"DonorType":{"Title":"Foundation"},"Program":{"Title":"Connected Oceans"},"FieldSite":{"Title":"Eastern Tropical Pacific Seascape"},"Duration":{"Title":"3"},"FundingStatus":{"Id":4,"Title":"Booked"},"Author":{"Title":"Ashleigh McGovern"},"Editor":{"Title":"Ashleigh McGovern"},"Id":20,"Project":"Eastern Tropical Pacific Seascape ","TotalCommitment":8650000.0,"ProgramCommitment":0.0,"FieldSiteCommitment":8650000.0,"Notes":null,"ID":20,"Modified":"2016-08-09T18:34:24Z","Created":"2016-06-25T20:38:36Z"},{"FiscalYear":{"Title":"2014"},"Donor":{"Title":"Swedish Postalcode Foundation"},"DonorType":{"Title":"Foundation"},"Program":{"Title":"Connected Oceans"},"FieldSite":{"Title":"Eastern Tropical Pacific Seascape"},"Duration":{"Title":"3"},"FundingStatus":{"Id":4,"Title":"Booked"},"Author":{"Title":"Ashleigh McGovern"},"Editor":{"Title":"Ashleigh McGovern"},"Id":21,"Project":"Costa Rica Mangroves","TotalCommitment":3122689.0,"ProgramCommitment":312269.0,"FieldSiteCommitment":2810420.0,"Notes":null,"ID":21,"Modified":"2016-09-12T12:38:20Z","Created":"2016-06-25T20:38:36Z"},{"FiscalYear":{"Title":"2016"},"Donor":{"Title":"Walton Family Foundation"},"DonorType":{"Title":"Foundation"},"Program":{"Title":"Climate Mitigation"},"Duration":{"Title":"1"},"FundingStatus":{"Id":4,"Title":"Booked"},"Author":{"Title":"Ashleigh McGovern"},"Editor":{"Title":"Ashleigh McGovern"},"Id":22,"Project":"Blue Carbon","TotalCommitment":250000.0,"ProgramCommitment":250000.0,"FieldSiteCommitment":0.0,"Notes":null,"ID":22,"Modified":"2016-07-06T22:06:55Z","Created":"2016-06-25T20:38:36Z"},{"FiscalYear":{"Title":"2016"},"Donor":{"Title":"The David and Lucile Packard Foundation"},"DonorType":{"Title":"Foundation"},"Program":{"Title":"Climate Mitigation"},"Duration":{"Title":"1"},"FundingStatus":{"Id":4,"Title":"Booked"},"Author":{"Title":"Ashleigh McGovern"},"Editor":{"Title":"Ashleigh McGovern"},"Id":23,"Project":"Exploring the connection between sustainable fisheries and biodiversity conservation.","TotalCommitment":300000.0,"ProgramCommitment":300000.0,"FieldSiteCommitment":0.0,"Notes":null,"ID":23,"Modified":"2016-07-06T22:06:55Z","Created":"2016-06-25T20:38:36Z"},{"FiscalYear":{"Title":"2016"},"Donor":{"Title":"Oceans 5"},"DonorType":{"Title":"Foundation"},"Program":{"Title":"Resilient Fisheries"},"FieldSite":{"Title":"Eastern Tropical Pacific Seascape"},"Duration":{"Title":"1"},"FundingStatus":{"Id":5,"Title":"Rejected"},"Author":{"Title":"Ashleigh McGovern"},"Editor":{"Title":"Ashleigh McGovern"},"Id":24,"Project":"Improving coastal fisheries in Panama, Hawaii, and New Caledonia","TotalCommitment":1500000.0,"ProgramCommitment":500000.0,"FieldSiteCommitment":1000000.0,"Notes":null,"ID":24,"Modified":"2016-08-09T18:34:15Z","Created":"2016-06-25T20:38:36Z"},{"FiscalYear":{"Title":"2017"},"Donor":{"Title":"Whitley Fund for Nature"},"DonorType":{"Title":"Foundation"},"Program":{"Title":"Connected Oceans"},"FieldSite":{"Title":"Bird's Head Seascape"},"Duration":{"Title":"1"},"FundingStatus":{"Id":5,"Title":"Rejected"},"Author":{"Title":"Ashleigh McGovern"},"Editor":{"Title":"Ashleigh McGovern"},"Id":25,"Project":"Making Marine Tourism Sustainable in the Anambas Islands","TotalCommitment":54000.0,"ProgramCommitment":0.0,"FieldSiteCommitment":54000.0,"Notes":null,"ID":25,"Modified":"2016-11-07T23:39:43Z","Created":"2016-06-25T20:38:37Z"},{"FiscalYear":{"Title":"2017"},"Donor":{"Title":"Hawai\u2018i Community Foundation"},"DonorType":{"Title":"Foundation"},"Program":{"Title":"Hawaii"},"FieldSite":{"Title":"Other"},"Duration":{"Title":"1"},"FundingStatus":{"Id":4,"Title":"Booked"},"Author":{"Title":"Ashleigh McGovern"},"Editor":{"Title":"Carolyn Hicks"},"Id":26,"Project":"Flex Grant Program (Hawaii Core Support)","TotalCommitment":10000.0,"ProgramCommitment":10000.0,"FieldSiteCommitment":0.0,"Notes":null,"ID":26,"Modified":"2016-11-30T20:46:52Z","Created":"2016-06-25T20:38:37Z"},{"FiscalYear":{"Title":"2013"},"Donor":{"Title":"Hawaiian Airlines"},"DonorType":{"Title":"Corporate"},"Program":{"Title":"Policy + Governance"},"Duration":{"Title":"1"},"FundingStatus":{"Id":4,"Title":"Booked"},"Author":{"Title":"Ashleigh McGovern"},"Editor":{"Title":"Ashleigh McGovern"},"Id":27,"Project":"Ocean Health Index - Hawaii Business Roundtable","TotalCommitment":25993.0,"ProgramCommitment":25993.0,"FieldSiteCommitment":0.0,"Notes":"Ocean Health Index","ID":27,"Modified":"2016-11-30T18:11:27Z","Created":"2016-06-25T20:38:37Z"},{"FiscalYear":{"Title":"2013"},"Donor":{"Title":"Hawaiian Tourism Authority"},"DonorType":{"Title":"Public"},"Program":{"Title":"Policy + Governance"},"Duration":{"Title":"1"},"FundingStatus":{"Id":4,"Title":"Booked"},"Author":{"Title":"Ashleigh McGovern"},"Editor":{"Title":"Ashleigh McGovern"},"Id":28,"Project":"Ocean Health Index - Hawaii Business Roundtable","TotalCommitment":30000.0,"ProgramCommitment":30000.0,"FieldSiteCommitment":0.0,"Notes":"Ocean Health Index","ID":28,"Modified":"2016-11-30T18:11:19Z","Created":"2016-06-25T20:38:37Z"},{"FiscalYear":{"Title":"2013"},"Donor":{"Title":"Thomas W. Haas Foundation (Tom Haas + Celina Adams)"},"DonorType":{"Title":"Foundation"},"Program":{"Title":"Core "},"Duration":{"Title":"5"},"FundingStatus":{"Id":4,"Title":"Booked"},"Author":{"Title":"Ashleigh McGovern"},"Editor":{"Title":"Ashleigh McGovern"},"Id":29,"Project":"Flexible","TotalCommitment":500000.0,"ProgramCommitment":500000.0,"FieldSiteCommitment":0.0,"Notes":null,"ID":29,"Modified":"2016-08-09T18:33:55Z","Created":"2016-06-25T20:38:37Z"},{"FiscalYear":{"Title":"2015"},"Donor":{"Title":"Rockefeller Foundation"},"DonorType":{"Title":"Foundation"},"Program":{"Title":"Resilient Fisheries"},"Duration":{"Title":"1"},"FundingStatus":{"Id":4,"Title":"Booked"},"Author":{"Title":"Ashleigh McGovern"},"Editor":{"Title":"Ashleigh McGovern"},"Id":30,"Project":"Project 1: Integrating Human Well-being, Ecosystem Services, and Biodiversity Information to Identify Vulnerable Coastal Populations Dependent on Fisheries and Other Marine Ecosystem Services for Their Food Security and Livelihoods","TotalCommitment":107000.0,"ProgramCommitment":107000.0,"FieldSiteCommitment":0.0,"Notes":null,"ID":30,"Modified":"2016-07-06T22:06:56Z","Created":"2016-06-25T20:38:37Z"},{"FiscalYear":{"Title":"2015"},"Donor":{"Title":"Walton Family Foundation"},"DonorType":{"Title":"Foundation"},"Program":{"Title":"Climate Mitigation"},"Duration":{"Title":"1"},"FundingStatus":{"Id":4,"Title":"Booked"},"Author":{"Title":"Ashleigh McGovern"},"Editor":{"Title":"Ashleigh McGovern"},"Id":31,"Project":"Blue Carbon Initiative","TotalCommitment":230000.0,"ProgramCommitment":230000.0,"FieldSiteCommitment":0.0,"Notes":null,"ID":31,"Modified":"2016-08-23T16:58:21Z","Created":"2016-06-25T20:38:37Z"},{"FiscalYear":{"Title":"2015"},"Donor":{"Title":"Waterloo Foundation"},"DonorType":{"Title":"Foundation"},"Program":{"Title":"Climate Mitigation"},"Duration":{"Title":"1"},"FundingStatus":{"Id":4,"Title":"Booked"},"Author":{"Title":"Ashleigh McGovern"},"Editor":{"Title":"Ashleigh McGovern"},"Id":32,"Project":"Blue Carbon Initiative","TotalCommitment":90000.0,"ProgramCommitment":90000.0,"FieldSiteCommitment":0.0,"Notes":null,"ID":32,"Modified":"2016-08-23T16:58:20Z","Created":"2016-06-25T20:38:37Z"},{"FiscalYear":{"Title":"2013"},"Donor":{"Title":"Waitt Foundation (Ted Waitt, Jacob James)"},"DonorType":{"Title":"Foundation"},"Program":{"Title":"Connected Oceans"},"FieldSite":{"Title":"Pacific Islands"},"FundingStatus":{"Id":4,"Title":"Booked"},"Author":{"Title":"Ashleigh McGovern"},"Editor":{"Title":"Ashleigh McGovern"},"Id":33,"Project":"Phoenix Islands Protected Area Trust","TotalCommitment":5000000.0,"ProgramCommitment":0.0,"FieldSiteCommitment":5000000.0,"Notes":null,"ID":33,"Modified":"2016-07-06T22:06:56Z","Created":"2016-06-25T20:38:37Z"},{"FiscalYear":{"Title":"2014"},"Donor":{"Title":"Robertson&nbsp; Foundation (Julian + Alex (son) Robertson)"},"DonorType":{"Title":"Foundation"},"Program":{"Title":"Connected Oceans"},"FieldSite":{"Title":"Pacific Islands"},"FundingStatus":{"Id":4,"Title":"Booked"},"Author":{"Title":"Ashleigh McGovern"},"Editor":{"Title":"Ashleigh McGovern"},"Id":34,"Project":"PIPA & CIMP: Science to Action","TotalCommitment":300000.0,"ProgramCommitment":0.0,"FieldSiteCommitment":300000.0,"Notes":null,"ID":34,"Modified":"2016-07-06T22:06:56Z","Created":"2016-06-25T20:38:37Z"},{"FiscalYear":{"Title":"2015"},"Donor":{"Title":"Chris Anderson"},"DonorType":{"Title":"Individual"},"Program":{"Title":"Connected Oceans"},"FieldSite":{"Title":"Bird's Head Seascape"},"Duration":{"Title":"1"},"FundingStatus":{"Id":4,"Title":"Booked"},"Author":{"Title":"Ashleigh McGovern"},"Editor":{"Title":"Ashleigh McGovern"},"Id":35,"Project":"Bird's Head Seascape - Kalabia Education Program","TotalCommitment":400000.0,"ProgramCommitment":0.0,"FieldSiteCommitment":400000.0,"Notes":null,"ID":35,"Modified":"2016-09-12T12:38:51Z","Created":"2016-06-25T20:38:37Z"},{"FiscalYear":{"Title":"2014"},"Donor":{"Title":"Mr. and Mrs. James Pigott"},"DonorType":{"Title":"Individual"},"Program":{"Title":"Connected Oceans"},"FieldSite":{"Title":"Pacific Islands"},"FundingStatus":{"Id":4,"Title":"Booked"},"Author":{"Title":"Ashleigh McGovern"},"Editor":{"Title":"Ashleigh McGovern"},"Id":36,"Project":"Flexible","TotalCommitment":2000000.0,"ProgramCommitment":0.0,"FieldSiteCommitment":2000000.0,"Notes":null,"ID":36,"Modified":"2016-07-06T22:06:56Z","Created":"2016-06-25T20:38:37Z"},{"FiscalYear":{"Title":"2014"},"Donor":{"Title":"Lisa and Alan Dynner"},"DonorType":{"Title":"Individual"},"Program":{"Title":"Connected Oceans"},"FieldSite":{"Title":"Pacific Islands"},"FundingStatus":{"Id":4,"Title":"Booked"},"Author":{"Title":"Ashleigh McGovern"},"Editor":{"Title":"Ashleigh McGovern"},"Id":37,"Project":"Pacific Oceanscape","TotalCommitment":50000.0,"ProgramCommitment":0.0,"FieldSiteCommitment":50000.0,"Notes":null,"ID":37,"Modified":"2016-07-06T22:06:56Z","Created":"2016-06-25T20:38:37Z"},{"FiscalYear":{"Title":"2014"},"Donor":{"Title":"Lisa and Alan Dynner"},"DonorType":{"Title":"Individual"},"Program":{"Title":"Connected Oceans"},"FieldSite":{"Title":"Pacific Islands"},"FundingStatus":{"Id":4,"Title":"Booked"},"Author":{"Title":"Ashleigh McGovern"},"Editor":{"Title":"Ashleigh McGovern"},"Id":38,"Project":"Pacific Oceanscape","TotalCommitment":75000.0,"ProgramCommitment":0.0,"FieldSiteCommitment":75000.0,"Notes":null,"ID":38,"Modified":"2016-07-06T22:06:57Z","Created":"2016-06-25T20:38:37Z"},{"FiscalYear":{"Title":"2015"},"Donor":{"Title":"Betty and Gordon Moore"},"DonorType":{"Title":"Individual"},"Program":{"Title":"Core "},"FieldSite":{"Title":"Other"},"Duration":{"Title":"1"},"FundingStatus":{"Id":4,"Title":"Booked"},"Author":{"Title":"Ashleigh McGovern"},"Editor":{"Title":"Ashleigh McGovern"},"Id":39,"Project":"Moore Center for Science ","TotalCommitment":3000000.0,"ProgramCommitment":0.0,"FieldSiteCommitment":3000000.0,"Notes":null,"ID":39,"Modified":"2016-08-23T16:58:18Z","Created":"2016-06-25T20:38:37Z"},{"FiscalYear":{"Title":"2014"},"Donor":{"Title":"Generation Foundation (Generation Investment; Mark Ferguson)"},"DonorType":{"Title":"Foundation"},"Program":{"Title":"Connected Oceans"},"FieldSite":{"Title":"Sulu-Sulawesi Seascape"},"FundingStatus":{"Id":4,"Title":"Booked"},"Author":{"Title":"Ashleigh McGovern"},"Editor":{"Title":"Ashleigh McGovern"},"Id":40,"Project":"Mangrove Restoration and Rehabilitation on the Philippines","TotalCommitment":30000.0,"ProgramCommitment":0.0,"FieldSiteCommitment":30000.0,"Notes":null,"ID":40,"Modified":"2016-07-06T22:06:57Z","Created":"2016-06-25T20:38:37Z"},{"FiscalYear":{"Title":"2014"},"Donor":{"Title":"Roddenberry Foundation (Heidi and Rod Roddenberry)"},"DonorType":{"Title":"Foundation"},"Program":{"Title":"Connected Oceans"},"FieldSite":{"Title":"Sulu-Sulawesi Seascape"},"FundingStatus":{"Id":4,"Title":"Booked"},"Author":{"Title":"Ashleigh McGovern"},"Editor":{"Title":"Ashleigh McGovern"},"Id":41,"Project":"Mangrove Restoration and Rehabilitation on the Philippines","TotalCommitment":28000.0,"ProgramCommitment":0.0,"FieldSiteCommitment":28000.0,"Notes":null,"ID":41,"Modified":"2016-07-06T22:06:57Z","Created":"2016-06-25T20:38:37Z"},{"FiscalYear":{"Title":"2014"},"Donor":{"Title":"Turing Foundation"},"DonorType":{"Title":"Foundation"},"Program":{"Title":"Connected Oceans"},"FieldSite":{"Title":"Sulu-Sulawesi Seascape"},"FundingStatus":{"Id":4,"Title":"Booked"},"Author":{"Title":"Ashleigh McGovern"},"Editor":{"Title":"Ashleigh McGovern"},"Id":42,"Project":"Sulu-Sulawesi Seascape","TotalCommitment":434000.0,"ProgramCommitment":0.0,"FieldSiteCommitment":434000.0,"Notes":null,"ID":42,"Modified":"2016-07-06T22:06:57Z","Created":"2016-06-25T20:38:37Z"},{"FiscalYear":{"Title":"2013"},"Donor":{"Title":"Richard Menzel"},"DonorType":{"Title":"Individual"},"Program":{"Title":"Connected Oceans"},"FieldSite":{"Title":"Sulu-Sulawesi Seascape"},"FundingStatus":{"Id":4,"Title":"Booked"},"Author":{"Title":"Ashleigh McGovern"},"Editor":{"Title":"Ashleigh McGovern"},"Id":43,"Project":"Philippines - mangroves","TotalCommitment":6000.0,"ProgramCommitment":0.0,"FieldSiteCommitment":6000.0,"Notes":null,"ID":43,"Modified":"2016-07-06T22:06:57Z","Created":"2016-06-25T20:38:37Z"},{"FiscalYear":{"Title":"2015"},"Donor":{"Title":"Dalio Foundation"},"DonorType":{"Title":"Individual"},"Program":{"Title":"Resilient Fisheries"},"FieldSite":{"Title":"Pacific Islands"},"Duration":{"Title":"2"},"FundingStatus":{"Id":4,"Title":"Booked"},"Author":{"Title":"Ashleigh McGovern"},"Editor":{"Title":"Ashleigh McGovern"},"Id":44,"Project":"Pacific Oceanscape - Global Tuna Initiative","TotalCommitment":2000000.0,"ProgramCommitment":0.0,"FieldSiteCommitment":2000000.0,"Notes":null,"ID":44,"Modified":"2016-07-06T22:06:57Z","Created":"2016-06-25T20:38:37Z"},{"FiscalYear":{"Title":"2017"},"Donor":{"Title":"Glenn Bucksbaum"},"DonorType":{"Title":"Individual"},"Program":{"Title":"Core "},"Duration":{"Title":"1"},"FundingStatus":{"Id":3,"Title":"Approved"},"Author":{"Title":"Ashleigh McGovern"},"Editor":{"Title":"Ashleigh McGovern"},"Id":45,"Project":"Seamount Expedition","TotalCommitment":70000.0,"ProgramCommitment":70000.0,"FieldSiteCommitment":0.0,"Notes":"Seamount Expedition","ID":45,"Modified":"2016-08-09T18:11:08Z","Created":"2016-06-25T20:38:37Z"},{"FiscalYear":{"Title":"2016"},"Donor":{"Title":"Richard Menzel"},"DonorType":{"Title":"Individual"},"Program":{"Title":"Resilient Fisheries"},"FieldSite":{"Title":"Abrolhos Seascape"},"Duration":{"Title":"1"},"FundingStatus":{"Id":4,"Title":"Booked"},"Author":{"Title":"Ashleigh McGovern"},"Editor":{"Title":"Ashleigh McGovern"},"Id":46,"Project":"Brazil - Match for Sustainable FIsheries Fund Gift","TotalCommitment":2000.0,"ProgramCommitment":0.0,"FieldSiteCommitment":2000.0,"Notes":null,"ID":46,"Modified":"2016-07-06T22:06:57Z","Created":"2016-06-25T20:38:37Z"},{"FiscalYear":{"Title":"2016"},"Donor":{"Title":"Betty and Gordon Moore"},"DonorType":{"Title":"Individual"},"Program":{"Title":"Core "},"FieldSite":{"Title":"Other"},"Duration":{"Title":"1"},"FundingStatus":{"Id":4,"Title":"Booked"},"Author":{"Title":"Ashleigh McGovern"},"Editor":{"Title":"Ashleigh McGovern"},"Id":47,"Project":"Science","TotalCommitment":3000000.0,"ProgramCommitment":0.0,"FieldSiteCommitment":3000000.0,"Notes":null,"ID":47,"Modified":"2016-07-06T22:06:57Z","Created":"2016-06-25T20:38:38Z"},{"FiscalYear":{"Title":"2016"},"Donor":{"Title":"Maureen Schafer"},"DonorType":{"Title":"Individual"},"Program":{"Title":"Core "},"FieldSite":{"Title":"Pacific Islands"},"Duration":{"Title":"1"},"FundingStatus":{"Id":4,"Title":"Booked"},"Author":{"Title":"Ashleigh McGovern"},"Editor":{"Title":"Ashleigh McGovern"},"Id":48,"Project":"Kiribati Oceans","TotalCommitment":5000.0,"ProgramCommitment":5000.0,"FieldSiteCommitment":0.0,"Notes":null,"ID":48,"Modified":"2017-04-07T15:00:53Z","Created":"2016-06-25T20:38:38Z"},{"FiscalYear":{"Title":"2016"},"Donor":{"Title":"Mr. and Mrs. James Pigott"},"DonorType":{"Title":"Individual"},"Program":{"Title":"Connected Oceans"},"FieldSite":{"Title":"Pacific Islands"},"Duration":{"Title":"1"},"FundingStatus":{"Id":4,"Title":"Booked"},"Author":{"Title":"Ashleigh McGovern"},"Editor":{"Title":"Ashleigh McGovern"},"Id":49,"Project":"Oceanscape","TotalCommitment":750000.0,"ProgramCommitment":0.0,"FieldSiteCommitment":750000.0,"Notes":null,"ID":49,"Modified":"2016-07-06T22:06:57Z","Created":"2016-06-25T20:38:38Z"},{"FiscalYear":{"Title":"2016"},"Donor":{"Title":"Trott Family Foundation (Byron Trott)"},"DonorType":{"Title":"Individual"},"Program":{"Title":"Core "},"Duration":{"Title":"1"},"FundingStatus":{"Id":4,"Title":"Booked"},"Author":{"Title":"Ashleigh McGovern"},"Editor":{"Title":"Ashleigh McGovern"},"Id":50,"Project":"Flexible","TotalCommitment":66000.0,"ProgramCommitment":66000.0,"FieldSiteCommitment":0.0,"Notes":null,"ID":50,"Modified":"2016-07-06T22:06:57Z","Created":"2016-06-25T20:38:38Z"},{"FiscalYear":{"Title":"2016"},"Donor":{"Title":"William \"Beau\" Wrigley, Jr."},"DonorType":{"Title":"Individual"},"Program":{"Title":"Core "},"Duration":{"Title":"1"},"FundingStatus":{"Id":4,"Title":"Booked"},"Author":{"Title":"Ashleigh McGovern"},"Editor":{"Title":"Ashleigh McGovern"},"Id":51,"Project":"Flexible","TotalCommitment":25000.0,"ProgramCommitment":25000.0,"FieldSiteCommitment":0.0,"Notes":null,"ID":51,"Modified":"2016-07-06T22:06:58Z","Created":"2016-06-25T20:38:38Z"},{"FiscalYear":{"Title":"2016"},"Donor":{"Title":"Wendy Benchley"},"DonorType":{"Title":"Individual"},"Program":{"Title":"Core "},"Duration":{"Title":"1"},"FundingStatus":{"Id":4,"Title":"Booked"},"Author":{"Title":"Ashleigh McGovern"},"Editor":{"Title":"Ashleigh McGovern"},"Id":52,"Project":"Flexible","TotalCommitment":20000.0,"ProgramCommitment":20000.0,"FieldSiteCommitment":0.0,"Notes":null,"ID":52,"Modified":"2016-07-06T22:06:58Z","Created":"2016-06-25T20:38:38Z"},{"FiscalYear":{"Title":"2016"},"Donor":{"Title":"Mr. and Mrs. Micael Wilsey (Eilsey, Bennett + Company)"},"DonorType":{"Title":"Individual"},"Program":{"Title":"Hawaii"},"Duration":{"Title":"1"},"FundingStatus":{"Id":4,"Title":"Booked"},"Author":{"Title":"Ashleigh McGovern"},"Editor":{"Title":"Ashleigh McGovern"},"Id":53,"Project":"General support","TotalCommitment":3000.0,"ProgramCommitment":3000.0,"FieldSiteCommitment":0.0,"Notes":null,"ID":53,"Modified":"2016-07-06T22:06:58Z","Created":"2016-06-25T20:38:38Z"},{"FiscalYear":{"Title":"2013"},"Donor":{"Title":"Wendy Benchley"},"DonorType":{"Title":"Individual"},"Program":{"Title":"Core "},"FundingStatus":{"Id":4,"Title":"Booked"},"Author":{"Title":"Ashleigh McGovern"},"Editor":{"Title":"Ashleigh McGovern"},"Id":54,"Project":"Flexible","TotalCommitment":10000.0,"ProgramCommitment":10000.0,"FieldSiteCommitment":0.0,"Notes":null,"ID":54,"Modified":"2016-08-23T16:58:07Z","Created":"2016-06-25T20:38:38Z"},{"FiscalYear":{"Title":"2013"},"Donor":{"Title":"Mr. Mike Velings and Ms. Amy Novogratz"},"DonorType":{"Title":"Individual"},"Program":{"Title":"Core "},"FundingStatus":{"Id":4,"Title":"Booked"},"Author":{"Title":"Ashleigh McGovern"},"Editor":{"Title":"Ashleigh McGovern"},"Id":55,"Project":"Fisheries","TotalCommitment":1000.0,"ProgramCommitment":1000.0,"FieldSiteCommitment":0.0,"Notes":null,"ID":55,"Modified":"2016-08-23T16:58:04Z","Created":"2016-06-25T20:38:38Z"},{"FiscalYear":{"Title":"2013"},"Donor":{"Title":"Mr. Edgar H. Schein"},"DonorType":{"Title":"Individual"},"Program":{"Title":"Core "},"FundingStatus":{"Id":4,"Title":"Booked"},"Author":{"Title":"Ashleigh McGovern"},"Editor":{"Title":"Ashleigh McGovern"},"Id":56,"Project":"Marine Core","TotalCommitment":5000.0,"ProgramCommitment":5000.0,"FieldSiteCommitment":0.0,"Notes":null,"ID":56,"Modified":"2016-08-23T16:58:03Z","Created":"2016-06-25T20:38:38Z"},{"FiscalYear":{"Title":"2013"},"Donor":{"Title":"Joe + Diane Steinberg"},"DonorType":{"Title":"Individual"},"Program":{"Title":"Core "},"FundingStatus":{"Id":4,"Title":"Booked"},"Author":{"Title":"Ashleigh McGovern"},"Editor":{"Title":"Ashleigh McGovern"},"Id":57,"Project":"Marine Core","TotalCommitment":1500000.0,"ProgramCommitment":1500000.0,"FieldSiteCommitment":0.0,"Notes":null,"ID":57,"Modified":"2016-08-23T16:58:01Z","Created":"2016-06-25T20:38:38Z"},{"FiscalYear":{"Title":"2014"},"Donor":{"Title":"Wendy Benchley"},"DonorType":{"Title":"Individual"},"Program":{"Title":"Core "},"FundingStatus":{"Id":4,"Title":"Booked"},"Author":{"Title":"Ashleigh McGovern"},"Editor":{"Title":"Ashleigh McGovern"},"Id":58,"Project":"Flexible","TotalCommitment":20000.0,"ProgramCommitment":20000.0,"FieldSiteCommitment":0.0,"Notes":null,"ID":58,"Modified":"2016-08-23T16:58:00Z","Created":"2016-06-25T20:38:38Z"},{"FiscalYear":{"Title":"2014"},"Donor":{"Title":"Lisa and Alan Dynner"},"DonorType":{"Title":"Individual"},"Program":{"Title":"Core "},"FundingStatus":{"Id":4,"Title":"Booked"},"Author":{"Title":"Ashleigh McGovern"},"Editor":{"Title":"Ashleigh McGovern"},"Id":59,"Project":"Flexible - ","TotalCommitment":50000.0,"ProgramCommitment":50000.0,"FieldSiteCommitment":0.0,"Notes":null,"ID":59,"Modified":"2016-08-23T16:58:00Z","Created":"2016-06-25T20:38:38Z"},{"FiscalYear":{"Title":"2014"},"Donor":{"Title":"Leslie and Ed Davies"},"DonorType":{"Title":"Individual"},"Program":{"Title":"Core "},"FundingStatus":{"Id":4,"Title":"Booked"},"Author":{"Title":"Ashleigh McGovern"},"Editor":{"Title":"Ashleigh McGovern"},"Id":60,"Project":"Flexible","TotalCommitment":20000.0,"ProgramCommitment":20000.0,"FieldSiteCommitment":0.0,"Notes":null,"ID":60,"Modified":"2016-08-23T16:57:52Z","Created":"2016-06-25T20:38:38Z"},{"FiscalYear":{"Title":"2014"},"Donor":{"Title":"Mr. Mike Velings and Ms. Amy Novogratz"},"DonorType":{"Title":"Individual"},"Program":{"Title":"Core "},"FundingStatus":{"Id":4,"Title":"Booked"},"Author":{"Title":"Ashleigh McGovern"},"Editor":{"Title":"Ashleigh McGovern"},"Id":61,"Project":"Fisheries -","TotalCommitment":20000.0,"ProgramCommitment":20000.0,"FieldSiteCommitment":0.0,"Notes":null,"ID":61,"Modified":"2016-08-23T16:57:51Z","Created":"2016-06-25T20:38:38Z"},{"FiscalYear":{"Title":"2014"},"Donor":{"Title":"James (Jim) Gordon"},"DonorType":{"Title":"Individual"},"Program":{"Title":"Core "},"FundingStatus":{"Id":4,"Title":"Booked"},"Author":{"Title":"Ashleigh McGovern"},"Editor":{"Title":"Ashleigh McGovern"},"Id":62,"Project":"Marine Core","TotalCommitment":50000.0,"ProgramCommitment":50000.0,"FieldSiteCommitment":0.0,"Notes":null,"ID":62,"Modified":"2016-08-23T16:57:51Z","Created":"2016-06-25T20:38:38Z"},{"FiscalYear":{"Title":"2014"},"Donor":{"Title":"Monica Seligmann"},"DonorType":{"Title":"Individual"},"Program":{"Title":"Core "},"FundingStatus":{"Id":4,"Title":"Booked"},"Author":{"Title":"Ashleigh McGovern"},"Editor":{"Title":"Ashleigh McGovern"},"Id":63,"Project":"Marine Core","TotalCommitment":10000.0,"ProgramCommitment":10000.0,"FieldSiteCommitment":0.0,"Notes":null,"ID":63,"Modified":"2016-08-23T16:57:51Z","Created":"2016-06-25T20:38:38Z"},{"FiscalYear":{"Title":"2014"},"Donor":{"Title":"Rubin Foundation"},"DonorType":{"Title":"Individual"},"Program":{"Title":"Core "},"FundingStatus":{"Id":4,"Title":"Booked"},"Author":{"Title":"Ashleigh McGovern"},"Editor":{"Title":"Ashleigh McGovern"},"Id":64,"Project":"Marine Core","TotalCommitment":10000.0,"ProgramCommitment":10000.0,"FieldSiteCommitment":0.0,"Notes":null,"ID":64,"Modified":"2016-08-23T16:57:51Z","Created":"2016-06-25T20:38:38Z"},{"FiscalYear":{"Title":"2014"},"Donor":{"Title":"Trott Family Foundation (Byron Trott)"},"DonorType":{"Title":"Individual"},"Program":{"Title":"Core "},"FundingStatus":{"Id":4,"Title":"Booked"},"Author":{"Title":"Ashleigh McGovern"},"Editor":{"Title":"Ashleigh McGovern"},"Id":65,"Project":"Marine Core","TotalCommitment":200000.0,"ProgramCommitment":200000.0,"FieldSiteCommitment":0.0,"Notes":null,"ID":65,"Modified":"2016-08-23T16:57:49Z","Created":"2016-06-25T20:38:39Z"},{"FiscalYear":{"Title":"2014"},"Donor":{"Title":"Bob and Lisa Margolis"},"DonorType":{"Title":"Individual"},"Program":{"Title":"Core "},"FundingStatus":{"Id":4,"Title":"Booked"},"Author":{"Title":"Ashleigh McGovern"},"Editor":{"Title":"Ashleigh McGovern"},"Id":66,"Project":"Flexible","TotalCommitment":50000.0,"ProgramCommitment":50000.0,"FieldSiteCommitment":0.0,"Notes":null,"ID":66,"Modified":"2016-07-06T22:06:59Z","Created":"2016-06-25T20:38:39Z"},{"FiscalYear":{"Title":"2016"},"Donor":{"Title":"Jurvetson"},"DonorType":{"Title":"Individual"},"Program":{"Title":"Hawaii"},"Duration":{"Title":"1"},"FundingStatus":{"Id":4,"Title":"Booked"},"Author":{"Title":"Ashleigh McGovern"},"Editor":{"Title":"Ashleigh McGovern"},"Id":67,"Project":"Flexible","TotalCommitment":25000.0,"ProgramCommitment":25000.0,"FieldSiteCommitment":0.0,"Notes":null,"ID":67,"Modified":"2016-07-06T22:06:59Z","Created":"2016-06-25T20:38:39Z"},{"FiscalYear":{"Title":"2016"},"Donor":{"Title":"Charlene + Denny Kabcenell"},"DonorType":{"Title":"Individual"},"Program":{"Title":"Hawaii"},"Duration":{"Title":"1"},"FundingStatus":{"Id":4,"Title":"Booked"},"Author":{"Title":"Ashleigh McGovern"},"Editor":{"Title":"Ashleigh McGovern"},"Id":68,"Project":"Flexible","TotalCommitment":25000.0,"ProgramCommitment":25000.0,"FieldSiteCommitment":0.0,"Notes":null,"ID":68,"Modified":"2016-07-06T22:06:59Z","Created":"2016-06-25T20:38:39Z"},{"FiscalYear":{"Title":"2015"},"Donor":{"Title":"Wendy Benchley"},"DonorType":{"Title":"Individual"},"Program":{"Title":"Core "},"FundingStatus":{"Id":4,"Title":"Booked"},"Author":{"Title":"Ashleigh McGovern"},"Editor":{"Title":"Ashleigh McGovern"},"Id":69,"Project":"Flexible","TotalCommitment":10000.0,"ProgramCommitment":10000.0,"FieldSiteCommitment":0.0,"Notes":null,"ID":69,"Modified":"2016-08-23T16:57:43Z","Created":"2016-06-25T20:38:39Z"},{"FiscalYear":{"Title":"2013"},"Donor":{"Title":"Gordon and Betty Moore Foundation"},"DonorType":{"Title":"Foundation"},"Program":{"Title":"Resilient Fisheries"},"FundingStatus":{"Id":4,"Title":"Booked"},"Author":{"Title":"Ashleigh McGovern"},"Editor":{"Title":"Ashleigh McGovern"},"Id":70,"Project":"Fisheries -","TotalCommitment":527951.0,"ProgramCommitment":527951.0,"FieldSiteCommitment":0.0,"Notes":null,"ID":70,"Modified":"2016-07-06T22:06:59Z","Created":"2016-06-25T20:38:39Z"},{"FiscalYear":{"Title":"2014"},"Donor":{"Title":"Rockefeller Foundation"},"DonorType":{"Title":"Foundation"},"Program":{"Title":"Resilient Fisheries"},"FundingStatus":{"Id":4,"Title":"Booked"},"Author":{"Title":"Ashleigh McGovern"},"Editor":{"Title":"Ashleigh McGovern"},"Id":71,"Project":"Developing a typology of fisheries management tools: Scaling up for success","TotalCommitment":174893.0,"ProgramCommitment":174893.0,"FieldSiteCommitment":0.0,"Notes":null,"ID":71,"Modified":"2016-07-06T22:06:59Z","Created":"2016-06-25T20:38:39Z"},{"FiscalYear":{"Title":"2015"},"Donor":{"Title":"Leslie and Ed Davies"},"DonorType":{"Title":"Individual"},"Program":{"Title":"Core "},"FundingStatus":{"Id":4,"Title":"Booked"},"Author":{"Title":"Ashleigh McGovern"},"Editor":{"Title":"Ashleigh McGovern"},"Id":72,"Project":"Flexible","TotalCommitment":25000.0,"ProgramCommitment":25000.0,"FieldSiteCommitment":0.0,"Notes":null,"ID":72,"Modified":"2016-08-23T16:57:40Z","Created":"2016-06-25T20:38:39Z"},{"FiscalYear":{"Title":"2016"},"Donor":{"Title":"Ann Luskey"},"DonorType":{"Title":"Individual"},"Program":{"Title":"Policy + Governance"},"Duration":{"Title":"1"},"FundingStatus":{"Id":4,"Title":"Booked"},"Author":{"Title":"Ashleigh McGovern"},"Editor":{"Title":"Ashleigh McGovern"},"Id":73,"Project":"Flexible","TotalCommitment":5000.0,"ProgramCommitment":5000.0,"FieldSiteCommitment":0.0,"Notes":"Ocean health index","ID":73,"Modified":"2016-11-30T18:11:00Z","Created":"2016-06-25T20:38:39Z"},{"FiscalYear":{"Title":"2013"},"Donor":{"Title":"Pulama Lanai"},"DonorType":{"Title":"Corporate"},"Program":{"Title":"Hawaii"},"FundingStatus":{"Id":4,"Title":"Booked"},"Author":{"Title":"Ashleigh McGovern"},"Editor":{"Title":"Ashleigh McGovern"},"Id":74,"Project":"Coastal Resource Management in Lanai","TotalCommitment":100000.0,"ProgramCommitment":100000.0,"FieldSiteCommitment":0.0,"Notes":null,"ID":74,"Modified":"2016-08-23T16:57:38Z","Created":"2016-06-25T20:38:39Z"},{"FiscalYear":{"Title":"2017"},"Donor":{"Title":"Leslie and Ed Davies"},"DonorType":{"Title":"Individual"},"Program":{"Title":"Core "},"Duration":{"Title":"1"},"FundingStatus":{"Id":1,"Title":"Development"},"Author":{"Title":"Ashleigh McGovern"},"Editor":{"Title":"Ashleigh McGovern"},"Id":75,"Project":"Flexible","TotalCommitment":25000.0,"ProgramCommitment":25000.0,"FieldSiteCommitment":0.0,"Notes":null,"ID":75,"Modified":"2016-07-06T22:06:59Z","Created":"2016-06-25T20:38:39Z"},{"FiscalYear":{"Title":"2017"},"Donor":{"Title":"Ric and Suzanne Kayne"},"DonorType":{"Title":"Individual"},"Program":{"Title":"Core "},"Duration":{"Title":"2"},"FundingStatus":{"Id":1,"Title":"Development"},"Author":{"Title":"Ashleigh McGovern"},"Editor":{"Title":"Ashleigh McGovern"},"Id":76,"Project":"Flexible","TotalCommitment":500000.0,"ProgramCommitment":500000.0,"FieldSiteCommitment":0.0,"Notes":null,"ID":76,"Modified":"2016-07-06T22:06:59Z","Created":"2016-06-25T20:38:39Z"},{"FiscalYear":{"Title":"2017"},"Donor":{"Title":"Joe + Diane Steinberg"},"DonorType":{"Title":"Individual"},"Program":{"Title":"Core "},"Duration":{"Title":"1"},"FundingStatus":{"Id":1,"Title":"Development"},"Author":{"Title":"Ashleigh McGovern"},"Editor":{"Title":"Ashleigh McGovern"},"Id":77,"Project":"Flexible","TotalCommitment":500000.0,"ProgramCommitment":500000.0,"FieldSiteCommitment":0.0,"Notes":null,"ID":77,"Modified":"2016-12-16T18:56:11Z","Created":"2016-06-25T20:38:39Z"},{"FiscalYear":{"Title":"2017"},"Donor":{"Title":"Lisa and Alan Dynner"},"DonorType":{"Title":"Individual"},"Program":{"Title":"Core "},"Duration":{"Title":"4"},"FundingStatus":{"Id":3,"Title":"Approved"},"Author":{"Title":"Ashleigh McGovern"},"Editor":{"Title":"Ashleigh McGovern"},"Id":78,"Project":"Flexible - captial campaign gift for new ocean center","TotalCommitment":1000000.0,"ProgramCommitment":1000000.0,"FieldSiteCommitment":0.0,"Notes":null,"ID":78,"Modified":"2016-09-12T12:36:25Z","Created":"2016-06-25T20:38:39Z"},{"FiscalYear":{"Title":"2013"},"Donor":{"Title":"Ulupono Initiative (Pam and Pierre Omidyar)"},"DonorType":{"Title":"Foundation"},"Program":{"Title":"Hawaii"},"FundingStatus":{"Id":4,"Title":"Booked"},"Author":{"Title":"Ashleigh McGovern"},"Editor":{"Title":"Ashleigh McGovern"},"Id":79,"Project":"Seafood traceability","TotalCommitment":146618.0,"ProgramCommitment":146618.0,"FieldSiteCommitment":0.0,"Notes":null,"ID":79,"Modified":"2016-08-23T16:57:34Z","Created":"2016-06-25T20:38:39Z"},{"FiscalYear":{"Title":"2013"},"Donor":{"Title":"Atherton Family Foundation"},"DonorType":{"Title":"Foundation"},"Program":{"Title":"Hawaii"},"FundingStatus":{"Id":4,"Title":"Booked"},"Author":{"Title":"Ashleigh McGovern"},"Editor":{"Title":"Ashleigh McGovern"},"Id":80,"Project":"Hawaii","TotalCommitment":122828.0,"ProgramCommitment":122828.0,"FieldSiteCommitment":0.0,"Notes":null,"ID":80,"Modified":"2016-08-23T16:57:30Z","Created":"2016-06-25T20:38:39Z"},{"FiscalYear":{"Title":"2016"},"Donor":{"Title":"Bob and Lisa Margolis"},"DonorType":{"Title":"Individual"},"Program":{"Title":"Core "},"Duration":{"Title":"2"},"FundingStatus":{"Id":5,"Title":"Rejected"},"Author":{"Title":"Ashleigh McGovern"},"Editor":{"Title":"Ashleigh McGovern"},"Id":81,"Project":"Flexible","TotalCommitment":300000.0,"ProgramCommitment":300000.0,"FieldSiteCommitment":0.0,"Notes":null,"ID":81,"Modified":"2016-07-20T13:03:59Z","Created":"2016-06-25T20:38:39Z"},{"FiscalYear":{"Title":"2016"},"Donor":{"Title":"W. Dexter Paine and Susan Paine"},"DonorType":{"Title":"Individual"},"Program":{"Title":"Global Tuna Initiative"},"FieldSite":{"Title":"Pacific Islands"},"Duration":{"Title":"1"},"FundingStatus":{"Id":5,"Title":"Rejected"},"Author":{"Title":"Ashleigh McGovern"},"Editor":{"Title":"Ashleigh McGovern"},"Id":82,"Project":"Global Tuna Initiative - Securing Country Support","TotalCommitment":850000.0,"ProgramCommitment":50000.0,"FieldSiteCommitment":800000.0,"Notes":null,"ID":82,"Modified":"2016-07-06T22:07:00Z","Created":"2016-06-25T20:38:39Z"},{"FiscalYear":{"Title":"2016"},"Donor":{"Title":"Mr. Mike Velings and Ms. Amy Novogratz"},"DonorType":{"Title":"Individual"},"Program":{"Title":"Resilient Fisheries"},"Duration":{"Title":"2"},"FundingStatus":{"Id":5,"Title":"Rejected"},"Author":{"Title":"Ashleigh McGovern"},"Editor":{"Title":"Ashleigh McGovern"},"Id":83,"Project":"Fisheries -","TotalCommitment":60000.0,"ProgramCommitment":60000.0,"FieldSiteCommitment":0.0,"Notes":null,"ID":83,"Modified":"2016-07-06T22:07:00Z","Created":"2016-06-25T20:38:39Z"},{"FiscalYear":{"Title":"2016"},"Donor":{"Title":"Betty and Gordon Moore"},"DonorType":{"Title":"Individual"},"Program":{"Title":"Hawaii"},"Duration":{"Title":"3"},"FundingStatus":{"Id":5,"Title":"Rejected"},"Author":{"Title":"Ashleigh McGovern"},"Editor":{"Title":"Ashleigh McGovern"},"Id":84,"Project":"Flexible","TotalCommitment":1500000.0,"ProgramCommitment":1500000.0,"FieldSiteCommitment":0.0,"Notes":null,"ID":84,"Modified":"2016-07-06T22:07:00Z","Created":"2016-06-25T20:38:39Z"},{"FiscalYear":{"Title":"2016"},"Donor":{"Title":"Dalio Foundation"},"DonorType":{"Title":"Individual"},"Program":{"Title":"Policy + Governance"},"FieldSite":{"Title":"Africa"},"Duration":{"Title":"1"},"FundingStatus":{"Id":3,"Title":"Approved"},"Author":{"Title":"Ashleigh McGovern"},"Editor":{"Title":"Ashleigh McGovern"},"Id":85,"Project":"Ocean Health Index - Marine Manager in Africa focal Region","TotalCommitment":50000.0,"ProgramCommitment":0.0,"FieldSiteCommitment":50000.0,"Notes":"Ocean Health Index","ID":85,"Modified":"2016-11-30T18:10:49Z","Created":"2016-06-25T20:38:39Z"},{"FiscalYear":{"Title":"2015"},"Donor":{"Title":"Eve & Ellis Short"},"DonorType":{"Title":"Individual"},"Program":{"Title":"Hawaii"},"FundingStatus":{"Id":4,"Title":"Booked"},"Author":{"Title":"Ashleigh McGovern"},"Editor":{"Title":"Ashleigh McGovern"},"Id":86,"Project":"Hawaii","TotalCommitment":50000.0,"ProgramCommitment":50000.0,"FieldSiteCommitment":0.0,"Notes":null,"ID":86,"Modified":"2016-07-06T22:07:00Z","Created":"2016-06-25T20:38:39Z"},{"FiscalYear":{"Title":"2017"},"Donor":{"Title":"Hans and Jayne Hufschmid"},"DonorType":{"Title":"Individual"},"Program":{"Title":"Policy + Governance"},"Duration":{"Title":"3"},"FundingStatus":{"Id":1,"Title":"Development"},"Author":{"Title":"Ashleigh McGovern"},"Editor":{"Title":"Ashleigh McGovern"},"Id":87,"Project":"Flexible","TotalCommitment":2000000.0,"ProgramCommitment":2000000.0,"FieldSiteCommitment":0.0,"Notes":"Ocean Health index","ID":87,"Modified":"2017-04-05T18:50:11Z","Created":"2016-06-25T20:38:39Z"},{"FiscalYear":{"Title":"2015"},"Donor":{"Title":"Ann Luskey"},"DonorType":{"Title":"Individual"},"Program":{"Title":"Policy + Governance"},"Duration":{"Title":"1"},"FundingStatus":{"Id":4,"Title":"Booked"},"Author":{"Title":"Ashleigh McGovern"},"Editor":{"Title":"Ashleigh McGovern"},"Id":88,"Project":"Flexible","TotalCommitment":5000.0,"ProgramCommitment":5000.0,"FieldSiteCommitment":0.0,"Notes":"Ocean Health index","ID":88,"Modified":"2016-11-30T18:10:35Z","Created":"2016-06-25T20:38:39Z"},{"FiscalYear":{"Title":"2015"},"Donor":{"Title":"Bob and Lisa Margolis"},"DonorType":{"Title":"Individual"},"Program":{"Title":"Policy + Governance"},"Duration":{"Title":"1"},"FundingStatus":{"Id":4,"Title":"Booked"},"Author":{"Title":"Ashleigh McGovern"},"Editor":{"Title":"Ashleigh McGovern"},"Id":89,"Project":"OHI or Climate Adaptation","TotalCommitment":25000.0,"ProgramCommitment":25000.0,"FieldSiteCommitment":0.0,"Notes":"Ocean Health Index","ID":89,"Modified":"2016-11-30T18:10:31Z","Created":"2016-06-25T20:38:40Z"},{"FiscalYear":{"Title":"2015"},"Donor":{"Title":"Aus Aid"},"DonorType":{"Title":"Public"},"Program":{"Title":"Connected Oceans"},"FieldSite":{"Title":"Bird's Head Seascape"},"FundingStatus":{"Id":4,"Title":"Booked"},"Author":{"Title":"Ashleigh McGovern"},"Editor":{"Title":"Ashleigh McGovern"},"Id":90,"Project":"Coral Triangle Initiative - Papua New Guinea","TotalCommitment":540000.0,"ProgramCommitment":0.0,"FieldSiteCommitment":540000.0,"Notes":null,"ID":90,"Modified":"2016-07-06T22:07:00Z","Created":"2016-06-25T20:38:40Z"},{"FiscalYear":{"Title":"2015"},"Donor":{"Title":"Aus Aid"},"DonorType":{"Title":"Public"},"Program":{"Title":"Connected Oceans"},"FieldSite":{"Title":"Bird's Head Seascape"},"FundingStatus":{"Id":4,"Title":"Booked"},"Author":{"Title":"Ashleigh McGovern"},"Editor":{"Title":"Ashleigh McGovern"},"Id":91,"Project":"Coral Triangle Initiative - Coral Reefs, Fisheries, and Food Security","TotalCommitment":1051513.0,"ProgramCommitment":0.0,"FieldSiteCommitment":1051513.0,"Notes":null,"ID":91,"Modified":"2016-07-06T22:07:00Z","Created":"2016-06-25T20:38:40Z"},{"FiscalYear":{"Title":"2015"},"Donor":{"Title":"Government of Kiribati"},"DonorType":{"Title":"Public"},"Program":{"Title":"Connected Oceans"},"FieldSite":{"Title":"Pacific Islands"},"FundingStatus":{"Id":4,"Title":"Booked"},"Author":{"Title":"Ashleigh McGovern"},"Editor":{"Title":"Ashleigh McGovern"},"Id":92,"Project":"PIPA Trust","TotalCommitment":2500000.0,"ProgramCommitment":0.0,"FieldSiteCommitment":2500000.0,"Notes":null,"ID":92,"Modified":"2016-07-06T22:07:00Z","Created":"2016-06-25T20:38:40Z"},{"FiscalYear":{"Title":"2017"},"Donor":{"Title":"National Oceanic and Atmospheric Administration"},"DonorType":{"Title":"Public"},"Program":{"Title":"Hawaii"},"FieldSite":{"Title":"Other"},"Duration":{"Title":"2"},"FundingStatus":{"Id":4,"Title":"Booked"},"Author":{"Title":"Ashleigh McGovern"},"Editor":{"Title":"Carolyn Hicks"},"Id":93,"Project":"Hookahua Building a Strong Foundation for a Statewide Fisheries Licensing System in Hawaii","TotalCommitment":242326.0,"ProgramCommitment":242326.0,"FieldSiteCommitment":0.0,"Notes":null,"ID":93,"Modified":"2016-11-30T20:49:14Z","Created":"2016-06-25T20:38:40Z"},{"FiscalYear":{"Title":"2016"},"Donor":{"Title":"Global Environment Facility (GEF)"},"DonorType":{"Title":"Public"},"Program":{"Title":"Policy + Governance"},"FieldSite":{"Title":"Eastern Tropical Pacific Seascape"},"Duration":{"Title":"4"},"FundingStatus":{"Id":4,"Title":"Booked"},"Author":{"Title":"Ashleigh McGovern"},"Editor":{"Title":"Ashleigh McGovern"},"Id":94,"Project":"Ecuador and Peru Assessments","TotalCommitment":941284.0,"ProgramCommitment":0.0,"FieldSiteCommitment":941284.0,"Notes":"Ocean Health Index","ID":94,"Modified":"2016-11-30T18:09:58Z","Created":"2016-06-25T20:38:40Z"},{"FiscalYear":{"Title":"2013"},"Donor":{"Title":"National Oceanic and Atmospheric Administration"},"DonorType":{"Title":"Public"},"Program":{"Title":"Hawaii"},"FundingStatus":{"Id":4,"Title":"Booked"},"Author":{"Title":"Ashleigh McGovern"},"Editor":{"Title":"Ashleigh McGovern"},"Id":95,"Project":"Local I'a: Developing a Community Supported Fishery in Hawaii","TotalCommitment":43000.0,"ProgramCommitment":43000.0,"FieldSiteCommitment":0.0,"Notes":null,"ID":95,"Modified":"2016-08-23T16:57:22Z","Created":"2016-06-25T20:38:40Z"},{"FiscalYear":{"Title":"2013"},"Donor":{"Title":"National Oceanic and Atmospheric Administration"},"DonorType":{"Title":"Public"},"Program":{"Title":"Hawaii"},"FundingStatus":{"Id":4,"Title":"Booked"},"Author":{"Title":"Ashleigh McGovern"},"Editor":{"Title":"Ashleigh McGovern"},"Id":96,"Project":"Hawaii - Lawai'a Camps","TotalCommitment":69780.0,"ProgramCommitment":69780.0,"FieldSiteCommitment":0.0,"Notes":null,"ID":96,"Modified":"2016-08-23T16:57:18Z","Created":"2016-06-25T20:38:40Z"},{"FiscalYear":{"Title":"2016"},"Donor":{"Title":"State of Hawaii"},"DonorType":{"Title":"Public"},"Program":{"Title":"Hawaii"},"FundingStatus":{"Id":4,"Title":"Booked"},"Author":{"Title":"Ashleigh McGovern"},"Editor":{"Title":"Ashleigh McGovern"},"Id":97,"Project":"Spawining Seasons: Continuation of the Hawaii Moon Calendar Project to strengthen community based monitoring and stewardship of nearshore fisheries","TotalCommitment":49934.0,"ProgramCommitment":49934.0,"FieldSiteCommitment":0.0,"Notes":null,"ID":97,"Modified":"2016-08-23T16:57:16Z","Created":"2016-06-25T20:38:40Z"},{"FiscalYear":{"Title":"2016"},"Donor":{"Title":"Hawaiian Tourism Authority"},"DonorType":{"Title":"Public"},"Program":{"Title":"Hawaii"},"Duration":{"Title":"1"},"FundingStatus":{"Id":4,"Title":"Booked"},"Author":{"Title":"Ashleigh McGovern"},"Editor":{"Title":"Ashleigh McGovern"},"Id":98,"Project":"Building the Sustainability of Near Shore Fisheries and Marine Resources in South Kona, Hawaii","TotalCommitment":20000.0,"ProgramCommitment":20000.0,"FieldSiteCommitment":0.0,"Notes":null,"ID":98,"Modified":"2016-07-06T22:07:01Z","Created":"2016-06-25T20:38:40Z"},{"FiscalYear":{"Title":"2013"},"Donor":{"Title":"Walton Family Foundation"},"DonorType":{"Title":"Foundation"},"Program":{"Title":"Climate Mitigation"},"FundingStatus":{"Id":4,"Title":"Booked"},"Author":{"Title":"Ashleigh McGovern"},"Editor":{"Title":"Ashleigh McGovern"},"Id":99,"Project":"Blue Carbon","TotalCommitment":200000.0,"ProgramCommitment":200000.0,"FieldSiteCommitment":0.0,"Notes":null,"ID":99,"Modified":"2016-08-23T16:57:14Z","Created":"2016-06-25T20:38:40Z"},{"FiscalYear":{"Title":"2013"},"Donor":{"Title":"Flora (Hewlett) Family Foundation"},"DonorType":{"Title":"Foundation"},"Program":{"Title":"Climate Mitigation"},"FundingStatus":{"Id":4,"Title":"Booked"},"Author":{"Title":"Ashleigh McGovern"},"Editor":{"Title":"Ashleigh McGovern"},"Id":100,"Project":"Blue Carbon Initiative","TotalCommitment":25000.0,"ProgramCommitment":25000.0,"FieldSiteCommitment":0.0,"Notes":null,"ID":100,"Modified":"2016-08-23T16:57:09Z","Created":"2016-06-25T20:38:40Z"},{"FiscalYear":{"Title":"2013"},"Donor":{"Title":"FFEM (French GEF)"},"DonorType":{"Title":"Foundation"},"Program":{"Title":"Climate Mitigation"},"FundingStatus":{"Id":4,"Title":"Booked"},"Author":{"Title":"Ashleigh McGovern"},"Editor":{"Title":"Ashleigh McGovern"},"Id":101,"Project":"Marine Climate Change","TotalCommitment":1615000.0,"ProgramCommitment":300000.0,"FieldSiteCommitment":1315000.0,"Notes":null,"ID":101,"Modified":"2016-09-12T12:43:24Z","Created":"2016-06-25T20:38:40Z"},{"FiscalYear":{"Title":"2016"},"Donor":{"Title":"National Oceanic and Atmospheric Administration"},"DonorType":{"Title":"Public"},"Program":{"Title":"Policy + Governance"},"Duration":{"Title":"2"},"FundingStatus":{"Id":4,"Title":"Booked"},"Author":{"Title":"Ashleigh McGovern"},"Editor":{"Title":"Ashleigh McGovern"},"Id":102,"Project":"OHI - Flexible","TotalCommitment":109992.0,"ProgramCommitment":109992.0,"FieldSiteCommitment":0.0,"Notes":"Ocean Health Index","ID":102,"Modified":"2016-11-30T18:13:09Z","Created":"2016-06-25T20:38:40Z"},{"FiscalYear":{"Title":"2017"},"Donor":{"Title":"Indian Ocean Commission - EUAid"},"DonorType":{"Title":"Public"},"Program":{"Title":"Policy + Governance"},"FieldSite":{"Title":"Africa"},"Duration":{"Title":"2"},"FundingStatus":{"Id":3,"Title":"Approved"},"Author":{"Title":"Ashleigh McGovern"},"Editor":{"Title":"Ashleigh McGovern"},"Id":103,"Project":"Kenya & Tanzania Assessments","TotalCommitment":112000.0,"ProgramCommitment":0.0,"FieldSiteCommitment":112000.0,"Notes":"Ocean Health Index","ID":103,"Modified":"2016-11-30T18:10:07Z","Created":"2016-06-25T20:38:40Z"},{"FiscalYear":{"Title":"2017"},"Donor":{"Title":"Indian Ocean Commission - EUAid"},"DonorType":{"Title":"Public"},"Program":{"Title":"Policy + Governance"},"FieldSite":{"Title":"Northern Mozambique Channel"},"Duration":{"Title":"2"},"FundingStatus":{"Id":3,"Title":"Approved"},"Author":{"Title":"Ashleigh McGovern"},"Editor":{"Title":"Ashleigh McGovern"},"Id":104,"Project":"Madagascar & Comoros Assessments","TotalCommitment":112000.0,"ProgramCommitment":0.0,"FieldSiteCommitment":112000.0,"Notes":"Ocean Health Index","ID":104,"Modified":"2017-04-05T18:49:52Z","Created":"2016-06-25T20:38:40Z"},{"FiscalYear":{"Title":"2013"},"Donor":{"Title":"National Aeronautics and Space Administration"},"DonorType":{"Title":"Public"},"Program":{"Title":"Climate Mitigation"},"FundingStatus":{"Id":4,"Title":"Booked"},"Author":{"Title":"Ashleigh McGovern"},"Editor":{"Title":"Ashleigh McGovern"},"Id":105,"Project":"Blue Carbon Initiative","TotalCommitment":120000.0,"ProgramCommitment":120000.0,"FieldSiteCommitment":0.0,"Notes":null,"ID":105,"Modified":"2016-08-23T16:57:03Z","Created":"2016-06-25T20:38:40Z"},{"FiscalYear":{"Title":"2017"},"Donor":{"Title":"Germany - BMUB-IKI"},"DonorType":{"Title":"Public"},"Program":{"Title":"Connected Oceans"},"FieldSite":{"Title":"Pacific Islands"},"Duration":{"Title":"4"},"FundingStatus":{"Id":5,"Title":"Rejected"},"Author":{"Title":"Ashleigh McGovern"},"Editor":{"Title":"Ashleigh McGovern"},"Id":106,"Project":"Climate adaptation in the Palau and Kiribati (inclusive Pacific Rising)","TotalCommitment":8668475.44,"ProgramCommitment":500352.48,"FieldSiteCommitment":8168122.96,"Notes":null,"ID":106,"Modified":"2017-01-03T20:02:23Z","Created":"2016-06-25T20:38:40Z"},{"FiscalYear":{"Title":"2016"},"Donor":{"Title":"National Oceanic and Atmospheric Administration"},"DonorType":{"Title":"Public"},"Program":{"Title":"Hawaii"},"Duration":{"Title":"3"},"FundingStatus":{"Id":5,"Title":"Rejected"},"Author":{"Title":"Ashleigh McGovern"},"Editor":{"Title":"Ashleigh McGovern"},"Id":107,"Project":"Strengthening Climate Adaptation and Resilence in Hawaii, Guam, and the Northern Mariana Islands","TotalCommitment":810000.0,"ProgramCommitment":810000.0,"FieldSiteCommitment":0.0,"Notes":null,"ID":107,"Modified":"2016-07-20T13:36:03Z","Created":"2016-06-25T20:38:40Z"},{"FiscalYear":{"Title":"2017"},"Donor":{"Title":"National Oceanic and Atmospheric Administration"},"DonorType":{"Title":"Public"},"Program":{"Title":"Hawaii"},"FieldSite":{"Title":"Other"},"Duration":{"Title":"4"},"FundingStatus":{"Id":5,"Title":"Rejected"},"Author":{"Title":"Ashleigh McGovern"},"Editor":{"Title":"Ashleigh McGovern"},"Id":108,"Project":"Strengthening Climate Adaptation and Resilience in Coastal Communities on Hawaii Island","TotalCommitment":250000.0,"ProgramCommitment":250000.0,"FieldSiteCommitment":0.0,"Notes":"COCA","ID":108,"Modified":"2016-11-08T19:04:10Z","Created":"2016-06-25T20:38:40Z"},{"FiscalYear":{"Title":"2013"},"Donor":{"Title":"Stena (Dan Sten Olssen, Claes Burglund & Kenneth MacLeod)"},"DonorType":{"Title":"Corporate"},"Program":{"Title":"Policy + Governance"},"FundingStatus":{"Id":4,"Title":"Booked"},"Author":{"Title":"Ashleigh McGovern"},"Editor":{"Title":"Ashleigh McGovern"},"Id":109,"Project":"OHI Flexible","TotalCommitment":500000.0,"ProgramCommitment":500000.0,"FieldSiteCommitment":0.0,"Notes":"Ocean Health Index","ID":109,"Modified":"2016-11-30T18:13:05Z","Created":"2016-06-25T20:38:40Z"},{"FiscalYear":{"Title":"2014"},"Donor":{"Title":"Pacific Life Foundation"},"DonorType":{"Title":"Corporate"},"Program":{"Title":"Policy + Governance"},"FundingStatus":{"Id":4,"Title":"Booked"},"Author":{"Title":"Ashleigh McGovern"},"Editor":{"Title":"Ashleigh McGovern"},"Id":110,"Project":"OHI Flexible","TotalCommitment":1000000.0,"ProgramCommitment":1000000.0,"FieldSiteCommitment":0.0,"Notes":"Ocean Health Index","ID":110,"Modified":"2016-11-30T18:12:50Z","Created":"2016-06-25T20:38:40Z"},{"FiscalYear":{"Title":"2014"},"Donor":{"Title":"New England Aquarium"},"DonorType":{"Title":"Corporate"},"Program":{"Title":"Policy + Governance"},"FundingStatus":{"Id":4,"Title":"Booked"},"Author":{"Title":"Ashleigh McGovern"},"Editor":{"Title":"Ashleigh McGovern"},"Id":111,"Project":"Ocean Health Index - Business workshop","TotalCommitment":32587.0,"ProgramCommitment":32587.0,"FieldSiteCommitment":0.0,"Notes":"Ocean Health index","ID":111,"Modified":"2016-11-30T18:04:12Z","Created":"2016-06-25T20:38:41Z"},{"FiscalYear":{"Title":"2014"},"Donor":{"Title":"Stena (Dan Sten Olssen, Claes Burglund & Kenneth MacLeod)"},"DonorType":{"Title":"Corporate"},"Program":{"Title":"Policy + Governance"},"FundingStatus":{"Id":4,"Title":"Booked"},"Author":{"Title":"Ashleigh McGovern"},"Editor":{"Title":"Ashleigh McGovern"},"Id":112,"Project":"OHI Flexible","TotalCommitment":500000.0,"ProgramCommitment":500000.0,"FieldSiteCommitment":0.0,"Notes":"Ocean Health Index","ID":112,"Modified":"2016-11-30T18:12:47Z","Created":"2016-06-25T20:38:41Z"},{"FiscalYear":{"Title":"2017"},"Donor":{"Title":"National Oceanic and Atmospheric Administration"},"DonorType":{"Title":"Public"},"Program":{"Title":"Hawaii"},"FieldSite":{"Title":"Other"},"Duration":{"Title":"2"},"FundingStatus":{"Id":5,"Title":"Rejected"},"Author":{"Title":"Ashleigh McGovern"},"Editor":{"Title":"Ashleigh McGovern"},"Id":113,"Project":"Revitalizing Traditional Hawaiian Fishponds to enhance aquaculture production and livelihoods for coastal communities","TotalCommitment":220000.0,"ProgramCommitment":220000.0,"FieldSiteCommitment":0.0,"Notes":"Saltonstall-Kennedy 2016 #1","ID":113,"Modified":"2016-10-31T20:27:45Z","Created":"2016-06-25T20:38:41Z"},{"FiscalYear":{"Title":"2015"},"Donor":{"Title":"National Aeronautics and Space Administration"},"DonorType":{"Title":"Public"},"Program":{"Title":"Climate Mitigation"},"FundingStatus":{"Id":4,"Title":"Booked"},"Author":{"Title":"Ashleigh McGovern"},"Editor":{"Title":"Ashleigh McGovern"},"Id":114,"Project":"Blue Carbon Initiative","TotalCommitment":60000.0,"ProgramCommitment":60000.0,"FieldSiteCommitment":0.0,"Notes":null,"ID":114,"Modified":"2016-08-23T16:56:58Z","Created":"2016-06-25T20:38:41Z"},{"FiscalYear":{"Title":"2015"},"Donor":{"Title":"Germany - BMUB-IKI"},"DonorType":{"Title":"Public"},"Program":{"Title":"Climate Mitigation"},"FundingStatus":{"Id":4,"Title":"Booked"},"Author":{"Title":"Ashleigh McGovern"},"Editor":{"Title":"Ashleigh McGovern"},"Id":115,"Project":"Climate Change","TotalCommitment":3500000.0,"ProgramCommitment":500000.0,"FieldSiteCommitment":3000000.0,"Notes":null,"ID":115,"Modified":"2016-09-12T12:43:42Z","Created":"2016-06-25T20:38:41Z"},{"FiscalYear":{"Title":"2016"},"Donor":{"Title":"National Oceanic and Atmospheric Administration"},"DonorType":{"Title":"Public"},"Program":{"Title":"Hawaii"},"FieldSite":{"Title":"Other"},"Duration":{"Title":"1"},"FundingStatus":{"Id":5,"Title":"Rejected"},"Author":{"Title":"Ashleigh McGovern"},"Editor":{"Title":"Ashleigh McGovern"},"Id":116,"Project":"Assessing enforcement effectiveness and understanding compliance behaviors in West Maui, Hawai'i","TotalCommitment":66573.0,"ProgramCommitment":66573.0,"FieldSiteCommitment":0.0,"Notes":null,"ID":116,"Modified":"2016-10-06T17:04:04Z","Created":"2016-06-25T20:38:41Z"},{"FiscalYear":{"Title":"2013"},"Donor":{"Title":"Ann Luskey"},"DonorType":{"Title":"Individual"},"Program":{"Title":"Policy + Governance"},"FundingStatus":{"Id":4,"Title":"Booked"},"Author":{"Title":"Ashleigh McGovern"},"Editor":{"Title":"Ashleigh McGovern"},"Id":117,"Project":"OHI Flexible","TotalCommitment":5000.0,"ProgramCommitment":5000.0,"FieldSiteCommitment":0.0,"Notes":"Ocean Health Index","ID":117,"Modified":"2016-11-30T18:12:43Z","Created":"2016-06-25T20:38:41Z"},{"FiscalYear":{"Title":"2013"},"Donor":{"Title":"Hans and Jayne Hufschmid"},"DonorType":{"Title":"Individual"},"Program":{"Title":"Policy + Governance"},"FundingStatus":{"Id":4,"Title":"Booked"},"Author":{"Title":"Ashleigh McGovern"},"Editor":{"Title":"Ashleigh McGovern"},"Id":118,"Project":"OHI Flexible","TotalCommitment":1000000.0,"ProgramCommitment":1000000.0,"FieldSiteCommitment":0.0,"Notes":"Ocean Health Index","ID":118,"Modified":"2016-11-30T18:12:33Z","Created":"2016-06-25T20:38:41Z"},{"FiscalYear":{"Title":"2014"},"Donor":{"Title":"Ann Luskey"},"DonorType":{"Title":"Individual"},"Program":{"Title":"Policy + Governance"},"FundingStatus":{"Id":4,"Title":"Booked"},"Author":{"Title":"Ashleigh McGovern"},"Editor":{"Title":"Ashleigh McGovern"},"Id":119,"Project":"OHI Flexible","TotalCommitment":5000.0,"ProgramCommitment":5000.0,"FieldSiteCommitment":0.0,"Notes":"Ocean Health Index","ID":119,"Modified":"2016-11-30T18:12:30Z","Created":"2016-06-25T20:38:41Z"},{"FiscalYear":{"Title":"2016"},"Donor":{"Title":"National Oceanic and Atmospheric Administration"},"DonorType":{"Title":"Public"},"Program":{"Title":"Hawaii"},"FieldSite":{"Title":"Other"},"Duration":{"Title":"2"},"FundingStatus":{"Id":5,"Title":"Rejected"},"Author":{"Title":"Ashleigh McGovern"},"Editor":{"Title":"Ashleigh McGovern"},"Id":120,"Project":"Climate Change impacts on food security and island reslilience: Assessing Marine resource vulnerability","TotalCommitment":274708.0,"ProgramCommitment":274708.0,"FieldSiteCommitment":0.0,"Notes":null,"ID":120,"Modified":"2016-10-05T20:14:23Z","Created":"2016-06-25T20:38:41Z"},{"FiscalYear":{"Title":"2016"},"Donor":{"Title":"National Science Foundation"},"DonorType":{"Title":"Public"},"Program":{"Title":"Hawaii"},"FieldSite":{"Title":"Other"},"Duration":{"Title":"2"},"FundingStatus":{"Id":5,"Title":"Rejected"},"Author":{"Title":"Ashleigh McGovern"},"Editor":{"Title":"Ashleigh McGovern"},"Id":121,"Project":"Coastal SEES: Fish Flow-Following Hawaiian Coarl Reef Fish from Spawning to Supper","TotalCommitment":162129.0,"ProgramCommitment":0.0,"FieldSiteCommitment":162129.0,"Notes":null,"ID":121,"Modified":"2016-10-06T17:03:41Z","Created":"2016-06-25T20:38:41Z"},{"FiscalYear":{"Title":"2017"},"Donor":{"Title":"National Aeronautics and Space Administration"},"DonorType":{"Title":"Public"},"Program":{"Title":"Climate Mitigation"},"Duration":{"Title":"2"},"FundingStatus":{"Id":3,"Title":"Approved"},"Author":{"Title":"Ashleigh McGovern"},"Editor":{"Title":"Ashleigh McGovern"},"Id":122,"Project":"Blue Carbon Scientific Working Group","TotalCommitment":126104.0,"ProgramCommitment":126104.0,"FieldSiteCommitment":0.0,"Notes":null,"ID":122,"Modified":"2016-08-23T16:56:34Z","Created":"2016-06-25T20:38:41Z"},{"FiscalYear":{"Title":"2017"},"Donor":{"Title":"Global Environment Facility (GEF)"},"DonorType":{"Title":"Public"},"Program":{"Title":"Connected Oceans"},"Duration":{"Title":"3"},"FundingStatus":{"Id":3,"Title":"Approved"},"Author":{"Title":"Ashleigh McGovern"},"Editor":{"Title":"Ashleigh McGovern"},"Id":123,"Project":"Partner exchanges to promote knowledge coordination between linked freshwater and marine GEF IW projects","TotalCommitment":50000.0,"ProgramCommitment":12000.0,"FieldSiteCommitment":38000.0,"Notes":null,"ID":123,"Modified":"2017-03-28T19:03:13Z","Created":"2016-06-25T20:38:41Z"},{"FiscalYear":{"Title":"2016"},"Donor":{"Title":"Mr. Edgar H. Schein"},"DonorType":{"Title":"Individual"},"Program":{"Title":"Core "},"FundingStatus":{"Id":4,"Title":"Booked"},"Author":{"Title":"Ashleigh McGovern"},"Editor":{"Title":"Ashleigh McGovern"},"Id":135,"Project":"Flexible","TotalCommitment":0.0,"ProgramCommitment":0.0,"FieldSiteCommitment":0.0,"Notes":null,"ID":135,"Modified":"2016-07-20T13:13:28Z","Created":"2016-07-07T18:14:59Z"},{"FiscalYear":{"Title":"2016"},"Donor":{"Title":"Mr. Edgar H. Schein"},"DonorType":{"Title":"Individual"},"Program":{"Title":"Core "},"FundingStatus":{"Id":4,"Title":"Booked"},"Author":{"Title":"Ashleigh McGovern"},"Editor":{"Title":"Ashleigh McGovern"},"Id":136,"Project":"Flexible","TotalCommitment":0.0,"ProgramCommitment":0.0,"FieldSiteCommitment":0.0,"Notes":null,"ID":136,"Modified":"2016-07-20T13:13:20Z","Created":"2016-07-07T18:15:58Z"},{"FiscalYear":{"Title":"2017"},"Donor":{"Title":"Bennett Jr and Delphina Dorrance"},"DonorType":{"Title":"Individual"},"Program":{"Title":"Hawaii"},"FieldSite":{"Title":"Other"},"FundingStatus":{"Id":5,"Title":"Rejected"},"Author":{"Title":"Ashleigh McGovern"},"Editor":{"Title":"Ashleigh McGovern"},"Id":137,"Project":"South Kona, Hawai\u02bbi Communities of Miloli\u02bbi and Honaunau and sharing project approaches with other communities of Hawai\u02bbi Island and the State of Hawai\u02bbi","TotalCommitment":176000.0,"ProgramCommitment":176000.0,"FieldSiteCommitment":0.0,"Notes":null,"ID":137,"Modified":"2016-10-11T12:54:32Z","Created":"2016-07-11T18:59:55Z"},{"FiscalYear":{"Title":"2016"},"Donor":{"Title":"Marin Community Foundation"},"DonorType":{"Title":"Foundation"},"Program":{"Title":"Climate Mitigation"},"Duration":{"Title":"1"},"FundingStatus":{"Id":4,"Title":"Booked"},"Author":{"Title":"Ashleigh McGovern"},"Editor":{"Title":"Ashleigh McGovern"},"Id":138,"Project":"Mangrove Blue Carbon","TotalCommitment":50000.0,"ProgramCommitment":50000.0,"FieldSiteCommitment":0.0,"Notes":null,"ID":138,"Modified":"2016-08-09T18:09:56Z","Created":"2016-07-11T19:00:46Z"},{"FiscalYear":{"Title":"2016"},"Donor":{"Title":"Mr. Edgar H. Schein"},"DonorType":{"Title":"Individual"},"Program":{"Title":"Core "},"Duration":{"Title":"1"},"FundingStatus":{"Id":4,"Title":"Booked"},"Author":{"Title":"Ashleigh McGovern"},"Editor":{"Title":"Ashleigh McGovern"},"Id":139,"Project":"Flexible","TotalCommitment":10000.0,"ProgramCommitment":10000.0,"FieldSiteCommitment":0.0,"Notes":null,"ID":139,"Modified":"2016-08-09T18:09:44Z","Created":"2016-07-11T19:01:23Z"},{"FiscalYear":{"Title":"2016"},"Donor":{"Title":"Charlene + Denny Kabcenell"},"DonorType":{"Title":"Individual"},"Program":{"Title":"Hawaii"},"FieldSite":{"Title":"Other"},"Duration":{"Title":"1"},"FundingStatus":{"Id":4,"Title":"Booked"},"Author":{"Title":"Ashleigh McGovern"},"Editor":{"Title":"Ashleigh McGovern"},"Id":140,"Project":"Flexible","TotalCommitment":25000.0,"ProgramCommitment":25000.0,"FieldSiteCommitment":0.0,"Notes":"Silicon Valley Foundation for Hawaii","ID":140,"Modified":"2016-10-11T12:54:39Z","Created":"2016-07-11T19:02:17Z"},{"FiscalYear":{"Title":"2016"},"Donor":{"Title":"Patrice Auld"},"DonorType":{"Title":"Individual"},"Program":{"Title":"Hawaii"},"Duration":{"Title":"1"},"FundingStatus":{"Id":4,"Title":"Booked"},"Author":{"Title":"Ashleigh McGovern"},"Editor":{"Title":"Ashleigh McGovern"},"Id":141,"Project":"Flexible","TotalCommitment":5000.0,"ProgramCommitment":5000.0,"FieldSiteCommitment":0.0,"Notes":null,"ID":141,"Modified":"2016-07-12T19:08:26Z","Created":"2016-07-11T19:06:04Z"},{"FiscalYear":{"Title":"2017"},"Donor":{"Title":"United States Soybean Export Council"},"DonorType":{"Title":"Corporate"},"Program":{"Title":"Resilient Fisheries"},"FieldSite":{"Title":"Other"},"Duration":{"Title":"1"},"FundingStatus":{"Id":3,"Title":"Approved"},"Author":{"Title":"Carolyn Hicks"},"Editor":{"Title":"Ashleigh McGovern"},"Id":155,"Project":"Aquaculture in Hawaii","TotalCommitment":75000.0,"ProgramCommitment":75000.0,"FieldSiteCommitment":0.0,"Notes":null,"ID":155,"Modified":"2016-11-15T20:44:02Z","Created":"2016-07-15T16:04:46Z"},{"FiscalYear":{"Title":"2017"},"Donor":{"Title":"Dalio Foundation"},"DonorType":{"Title":"Individual"},"Program":{"Title":"Core "},"FieldSite":{"Title":"Pacific Islands"},"Duration":{"Title":"1"},"FundingStatus":{"Id":5,"Title":"Rejected"},"Author":{"Title":"Ashleigh McGovern"},"Editor":{"Title":"Ashleigh McGovern"},"Id":156,"Project":"Seamount Expedition in New Caledonia","TotalCommitment":650000.0,"ProgramCommitment":0.0,"FieldSiteCommitment":650000.0,"Notes":"This is to reprogram funds from Ray Dalio's original commitment in 2014","ID":156,"Modified":"2016-11-14T18:01:10Z","Created":"2016-07-20T13:08:02Z"},{"FiscalYear":{"Title":"2017"},"Donor":{"Title":"Germany - KfW / BMZ"},"DonorType":{"Title":"Public"},"Program":{"Title":"Connected Oceans"},"FieldSite":{"Title":"Bird's Head Seascape"},"Duration":{"Title":"3"},"FundingStatus":{"Id":2,"Title":"Submitted"},"Author":{"Title":"Ashleigh McGovern"},"Editor":{"Title":"Ashleigh McGovern"},"Id":157,"Project":"Expanding sustainable marine resource management through building marine protected area networks in the coral triangle","TotalCommitment":2586556.0,"ProgramCommitment":152752.0,"FieldSiteCommitment":2433804.0,"Notes":"CTI - Blue Action Fund;","ID":157,"Modified":"2016-11-29T01:03:25Z","Created":"2016-07-20T13:09:50Z"},{"FiscalYear":{"Title":"2017"},"Donor":{"Title":"Germany - KfW / BMZ"},"DonorType":{"Title":"Public"},"Program":{"Title":"Connected Oceans"},"FieldSite":{"Title":"Northern Mozambique Channel"},"Duration":{"Title":"3"},"FundingStatus":{"Id":2,"Title":"Submitted"},"Author":{"Title":"Ashleigh McGovern"},"Editor":{"Title":"Ashleigh McGovern"},"Id":158,"Project":"Community based management of marine protected areas in northern madagascar and beyond","TotalCommitment":1884272.0,"ProgramCommitment":193999.0,"FieldSiteCommitment":1690273.0,"Notes":"ETPS - Blue Action Fund Includes budget for 20% OHI manager based in Nairobi","ID":158,"Modified":"2016-11-30T18:21:07Z","Created":"2016-07-20T13:10:29Z"},{"FiscalYear":{"Title":"2017"},"Donor":{"Title":"Germany - KfW / BMZ"},"DonorType":{"Title":"Public"},"Program":{"Title":"Connected Oceans"},"FieldSite":{"Title":"Eastern Tropical Pacific Seascape"},"Duration":{"Title":"3"},"FundingStatus":{"Id":2,"Title":"Submitted"},"Author":{"Title":"Ashleigh McGovern"},"Editor":{"Title":"Ashleigh McGovern"},"Id":159,"Project":"Fishing for a prosperous future: Making the Eastern Tropical Pacific Marine Protected Area network a driver of local community sustainable development","TotalCommitment":3184939.0,"ProgramCommitment":235217.0,"FieldSiteCommitment":2949722.0,"Notes":"Blue Action Fund\n\nBlue Action Fund was not capitalized","ID":159,"Modified":"2016-11-29T01:03:08Z","Created":"2016-07-20T13:11:00Z"},{"FiscalYear":{"Title":"2017"},"Donor":{"Title":"Pulama Lanai"},"DonorType":{"Title":"Foundation"},"Program":{"Title":"Hawaii"},"FieldSite":{"Title":"Other"},"Duration":{"Title":"1"},"FundingStatus":{"Id":3,"Title":"Approved"},"Author":{"Title":"Ashleigh McGovern"},"Editor":{"Title":"Ashleigh McGovern"},"Id":162,"Project":"Lanai Coastal Resiliency Planning","TotalCommitment":50000.0,"ProgramCommitment":50000.0,"FieldSiteCommitment":0.0,"Notes":"Larry Ellison","ID":162,"Modified":"2016-12-16T18:33:03Z","Created":"2016-08-12T01:43:45Z"},{"FiscalYear":{"Title":"2017"},"Donor":{"Title":"Ulupono Initiative (Pam and Pierre Omidyar)"},"DonorType":{"Title":"Foundation"},"Program":{"Title":"Hawaii"},"FieldSite":{"Title":"None"},"Duration":{"Title":"1"},"FundingStatus":{"Id":3,"Title":"Approved"},"Author":{"Title":"Ashleigh McGovern"},"Editor":{"Title":"Ashleigh McGovern"},"Id":164,"Project":"Fishpond Project","TotalCommitment":17400.0,"ProgramCommitment":17400.0,"FieldSiteCommitment":0.0,"Notes":null,"ID":164,"Modified":"2016-08-15T13:02:03Z","Created":"2016-08-15T13:02:03Z"},{"FiscalYear":{"Title":"2017"},"Donor":{"Title":"USAID"},"DonorType":{"Title":"Public"},"Program":{"Title":"Connected Oceans"},"FieldSite":{"Title":"Pacific Islands"},"Duration":{"Title":"3"},"FundingStatus":{"Id":5,"Title":"Rejected"},"Author":{"Title":"Ashleigh McGovern"},"Editor":{"Title":"Ashleigh McGovern"},"Id":165,"Project":"Lau Seascape","TotalCommitment":225000.0,"ProgramCommitment":0.0,"FieldSiteCommitment":225000.0,"Notes":"US Dept of State","ID":165,"Modified":"2016-10-31T20:31:39Z","Created":"2016-08-15T13:03:07Z"},{"FiscalYear":{"Title":"2017"},"Donor":{"Title":"Alan Eustace"},"DonorType":{"Title":"Individual"},"Program":{"Title":"Core "},"FieldSite":{"Title":"None"},"Duration":{"Title":"1"},"FundingStatus":{"Id":3,"Title":"Approved"},"Author":{"Title":"Ashleigh McGovern"},"Editor":{"Title":"Ashleigh McGovern"},"Id":166,"Project":"Hawaii Seamount Expedition","TotalCommitment":65000.0,"ProgramCommitment":65000.0,"FieldSiteCommitment":0.0,"Notes":null,"ID":166,"Modified":"2016-09-29T13:50:46Z","Created":"2016-08-15T13:05:26Z"},{"FiscalYear":{"Title":"2017"},"Donor":{"Title":"Seth Neiman"},"DonorType":{"Title":"Individual"},"Program":{"Title":"Core "},"FieldSite":{"Title":"None"},"Duration":{"Title":"1"},"FundingStatus":{"Id":3,"Title":"Approved"},"Author":{"Title":"Ashleigh McGovern"},"Editor":{"Title":"Carolyn Hicks"},"Id":167,"Project":"Hawaii Seamount Expedition","TotalCommitment":50000.0,"ProgramCommitment":50000.0,"FieldSiteCommitment":0.0,"Notes":null,"ID":167,"Modified":"2017-03-28T20:22:47Z","Created":"2016-08-15T13:05:56Z"},{"FiscalYear":{"Title":"2017"},"Donor":{"Title":"Credit Swiss"},"DonorType":{"Title":"Corporate"},"Program":{"Title":"Resilient Fisheries"},"FieldSite":{"Title":"Other"},"Duration":{"Title":"1"},"FundingStatus":{"Id":3,"Title":"Approved"},"Author":{"Title":"Ashleigh McGovern"},"Editor":{"Title":"Ashleigh McGovern"},"Id":168,"Project":"Sustainable Fisheries Toolkit","TotalCommitment":200000.0,"ProgramCommitment":160000.0,"FieldSiteCommitment":40000.0,"Notes":null,"ID":168,"Modified":"2016-10-31T20:28:20Z","Created":"2016-08-15T13:08:41Z"},{"FiscalYear":{"Title":"2017"},"Donor":{"Title":"Darwin Initiative"},"DonorType":{"Title":"Foundation"},"Program":{"Title":"Policy + Governance"},"FieldSite":{"Title":"Pacific Islands"},"Duration":{"Title":"2"},"FundingStatus":{"Id":5,"Title":"Rejected"},"Author":{"Title":"Ashleigh McGovern"},"Editor":{"Title":"Ashleigh McGovern"},"Id":169,"Project":"PIPA Whole Domain management plan using an integrated framework approach","TotalCommitment":300000.0,"ProgramCommitment":0.0,"FieldSiteCommitment":300000.0,"Notes":"Whole Domain","ID":169,"Modified":"2016-11-30T18:20:20Z","Created":"2016-08-15T13:10:11Z"},{"FiscalYear":{"Title":"2017"},"Donor":{"Title":"Gordon and Betty Moore Foundation"},"DonorType":{"Title":"Foundation"},"Program":{"Title":"Core "},"FieldSite":{"Title":"None"},"Duration":{"Title":"1"},"FundingStatus":{"Id":3,"Title":"Approved"},"Author":{"Title":"Ashleigh McGovern"},"Editor":{"Title":"Ashleigh McGovern"},"Id":172,"Project":"Flexible","TotalCommitment":5000.0,"ProgramCommitment":5000.0,"FieldSiteCommitment":0.0,"Notes":"In honor of Aulani's presentation to the board of directors August 2016","ID":172,"Modified":"2016-09-12T19:35:01Z","Created":"2016-09-12T19:35:01Z"},{"FiscalYear":{"Title":"2017"},"Donor":{"Title":"Wendy Benchley"},"DonorType":{"Title":"Individual"},"Program":{"Title":"Core "},"FieldSite":{"Title":"None"},"Duration":{"Title":"1"},"FundingStatus":{"Id":3,"Title":"Approved"},"Author":{"Title":"Ashleigh McGovern"},"Editor":{"Title":"Ashleigh McGovern"},"Id":175,"Project":"Flexible","TotalCommitment":20000.0,"ProgramCommitment":20000.0,"FieldSiteCommitment":0.0,"Notes":null,"ID":175,"Modified":"2016-09-29T13:39:35Z","Created":"2016-09-29T13:39:35Z"},{"FiscalYear":{"Title":"2017"},"Donor":{"Title":"National Fishery and Wildlife Foundation (NFWF)"},"DonorType":{"Title":"Foundation"},"Program":{"Title":"Hawaii"},"FieldSite":{"Title":"Other"},"Duration":{"Title":"1"},"FundingStatus":{"Id":3,"Title":"Approved"},"Author":{"Title":"Ashleigh McGovern"},"Editor":{"Title":"Ashleigh McGovern"},"Id":177,"Project":"Main Hawaiian Islands Multi-Fishery Traceability Implementation","TotalCommitment":81310.0,"ProgramCommitment":81310.0,"FieldSiteCommitment":0.0,"Notes":"Connected to Ulupono Initiative of same project name","ID":177,"Modified":"2016-10-31T20:28:15Z","Created":"2016-10-04T20:02:51Z"},{"FiscalYear":{"Title":"2017"},"Donor":{"Title":"Ulupono Initiative (Pam and Pierre Omidyar)"},"DonorType":{"Title":"Foundation"},"Program":{"Title":"Hawaii"},"FieldSite":{"Title":"Other"},"Duration":{"Title":"1"},"FundingStatus":{"Id":2,"Title":"Submitted"},"Author":{"Title":"Ashleigh McGovern"},"Editor":{"Title":"Ashleigh McGovern"},"Id":178,"Project":"Main Hawaiian Islands multi-fishery traceability implementation","TotalCommitment":45000.0,"ProgramCommitment":45000.0,"FieldSiteCommitment":0.0,"Notes":"Connected to NFWF grant of same name","ID":178,"Modified":"2016-10-06T17:02:59Z","Created":"2016-10-06T17:02:41Z"},{"FiscalYear":{"Title":"2017"},"Donor":{"Title":"Millennium Innovation Lab"},"DonorType":{"Title":"Foundation"},"Program":{"Title":"Hawaii"},"FieldSite":{"Title":"Other"},"Duration":{"Title":"1"},"FundingStatus":{"Id":5,"Title":"Rejected"},"Author":{"Title":"Ashleigh McGovern"},"Editor":{"Title":"Ashleigh McGovern"},"Id":179,"Project":"Monitoring Fishponds","TotalCommitment":25000.0,"ProgramCommitment":25000.0,"FieldSiteCommitment":0.0,"Notes":null,"ID":179,"Modified":"2016-11-07T20:26:52Z","Created":"2016-10-06T17:12:29Z"},{"FiscalYear":{"Title":"2017"},"Donor":{"Title":"George Meyer and Maria Semple"},"DonorType":{"Title":"Individual"},"Program":{"Title":"Core "},"FieldSite":{"Title":"None"},"Duration":{"Title":"1"},"FundingStatus":{"Id":4,"Title":"Booked"},"Author":{"Title":"Ashleigh McGovern"},"Editor":{"Title":"Ashleigh McGovern"},"Id":181,"Project":"Flexible","TotalCommitment":30000.0,"ProgramCommitment":30000.0,"FieldSiteCommitment":0.0,"Notes":null,"ID":181,"Modified":"2016-10-31T18:50:08Z","Created":"2016-10-31T18:50:08Z"},{"FiscalYear":{"Title":"2017"},"Donor":{"Title":"Global Environment Facility (GEF)"},"DonorType":{"Title":"Public"},"Program":{"Title":"Connected Oceans"},"FieldSite":{"Title":"None"},"Duration":{"Title":"2"},"FundingStatus":{"Id":3,"Title":"Approved"},"Author":{"Title":"Ashleigh McGovern"},"Editor":{"Title":"Ashleigh McGovern"},"Id":182,"Project":"LME: Learn ","TotalCommitment":133000.0,"ProgramCommitment":113000.0,"FieldSiteCommitment":20000.0,"Notes":"GEF-International Waters\nPartner exchanges to promote knowledge coordination between linked freshwater and marine GEF IW projects","ID":182,"Modified":"2017-04-07T15:00:31Z","Created":"2016-10-31T19:41:21Z"},{"FiscalYear":{"Title":"2017"},"Donor":{"Title":"Mr. and Mrs. James Pigott"},"DonorType":{"Title":"Individual"},"Program":{"Title":"Connected Oceans"},"FieldSite":{"Title":"None"},"Duration":{"Title":"1"},"FundingStatus":{"Id":3,"Title":"Approved"},"Author":{"Title":"Ashleigh McGovern"},"Editor":{"Title":"Ashleigh McGovern"},"Id":183,"Project":"Pacific Oceanscape","TotalCommitment":1300000.0,"ProgramCommitment":200000.0,"FieldSiteCommitment":1100000.0,"Notes":null,"ID":183,"Modified":"2016-12-20T15:58:15Z","Created":"2016-10-31T20:33:01Z"},{"FiscalYear":{"Title":"2017"},"Donor":{"Title":"Laney Thornton"},"DonorType":{"Title":"Individual"},"Program":{"Title":"Resilient Fisheries"},"FieldSite":{"Title":"Other"},"Duration":{"Title":"2"},"FundingStatus":{"Id":5,"Title":"Rejected"},"Author":{"Title":"Ashleigh McGovern"},"Editor":{"Title":"Ashleigh McGovern"},"Id":184,"Project":"Flexible","TotalCommitment":100000.0,"ProgramCommitment":100000.0,"FieldSiteCommitment":0.0,"Notes":null,"ID":184,"Modified":"2016-12-20T15:58:31Z","Created":"2016-11-18T19:05:10Z"},{"FiscalYear":{"Title":"2017"},"Donor":{"Title":"Jennifer Caldwell and John Fisher"},"DonorType":{"Title":"Individual"},"Program":{"Title":"Climate Mitigation"},"FieldSite":{"Title":"Bird's Head Seascape"},"Duration":{"Title":"1"},"FundingStatus":{"Id":3,"Title":"Approved"},"Author":{"Title":"Ashleigh McGovern"},"Editor":{"Title":"Ashleigh McGovern"},"Id":185,"Project":"Unlocking Potential of Blue Carbon","TotalCommitment":200000.0,"ProgramCommitment":150000.0,"FieldSiteCommitment":50000.0,"Notes":"the completion of the first blue carbon conservation project to gain VCS carbon credits in Kaimana, Indonesia, accelerate integration of blue carbon into climate policy in Indonesia and other priority countries, and create the methodologies for the creation of blue carbon credits globally","ID":185,"Modified":"2016-12-16T19:16:26Z","Created":"2016-11-28T14:22:23Z"},{"FiscalYear":{"Title":"2017"},"Donor":{"Title":"Pam Omidyar"},"DonorType":{"Title":"Individual"},"Program":{"Title":"Core "},"FieldSite":{"Title":"None"},"Duration":{"Title":"1"},"FundingStatus":{"Id":3,"Title":"Approved"},"Author":{"Title":"Ashleigh McGovern"},"Editor":{"Title":"Ashleigh McGovern"},"Id":186,"Project":"Flexible","TotalCommitment":5000.0,"ProgramCommitment":5000.0,"FieldSiteCommitment":0.0,"Notes":null,"ID":186,"Modified":"2016-11-28T14:23:10Z","Created":"2016-11-28T14:23:08Z"},{"FiscalYear":{"Title":"2017"},"Donor":{"Title":"Ann Luskey"},"DonorType":{"Title":"Individual"},"Program":{"Title":"Policy + Governance"},"FieldSite":{"Title":"None"},"Duration":{"Title":"1"},"FundingStatus":{"Id":1,"Title":"Development"},"Author":{"Title":"Ashleigh McGovern"},"Editor":{"Title":"Ashleigh McGovern"},"Id":187,"Project":"OHI Flexible","TotalCommitment":5000.0,"ProgramCommitment":5000.0,"FieldSiteCommitment":0.0,"Notes":"Ocean Health Index","ID":187,"Modified":"2016-11-30T18:16:09Z","Created":"2016-11-28T16:30:16Z"},{"FiscalYear":{"Title":"2017"},"Donor":{"Title":"Hawai\u2018i Community Foundation"},"DonorType":{"Title":"Foundation"},"Program":{"Title":"Hawaii"},"FieldSite":{"Title":"None"},"Duration":{"Title":"1"},"FundingStatus":{"Id":3,"Title":"Approved"},"Author":{"Title":"Ashleigh McGovern"},"Editor":{"Title":"Ashleigh McGovern"},"Id":189,"Project":"HI Flexible","TotalCommitment":20000.0,"ProgramCommitment":10000.0,"FieldSiteCommitment":10000.0,"Notes":"Traut Carson Fund at the Hawaii Community Foundation","ID":189,"Modified":"2016-12-01T19:14:29Z","Created":"2016-12-01T19:14:29Z"},{"FiscalYear":{"Title":"2017"},"Donor":{"Title":"Dawn Arnall"},"DonorType":{"Title":"Individual"},"Program":{"Title":"Connected Oceans"},"FieldSite":{"Title":"Bird's Head Seascape"},"Duration":{"Title":"3"},"FundingStatus":{"Id":3,"Title":"Approved"},"Author":{"Title":"Laure Katz"},"Editor":{"Title":"Laure Katz"},"Id":192,"Project":"Bird's Head Seascape","TotalCommitment":1500000.0,"ProgramCommitment":300000.0,"FieldSiteCommitment":1200000.0,"Notes":null,"ID":192,"Modified":"2016-12-12T07:50:28Z","Created":"2016-12-12T07:50:28Z"},{"FiscalYear":{"Title":"2017"},"Donor":{"Title":"State of Hawaii"},"DonorType":{"Title":"Public"},"Program":{"Title":"Hawaii"},"FieldSite":{"Title":"Other"},"Duration":{"Title":"1"},"FundingStatus":{"Id":3,"Title":"Approved"},"Author":{"Title":"Ashleigh McGovern"},"Editor":{"Title":"Ashleigh McGovern"},"Id":194,"Project":"Revitalizing Traditional Hawaiian Fishponds to enhance aquaculture production and livelihoods for coastal communities","TotalCommitment":150000.0,"ProgramCommitment":150000.0,"FieldSiteCommitment":0.0,"Notes":null,"ID":194,"Modified":"2016-12-21T13:39:17Z","Created":"2016-12-21T13:39:17Z"},{"FiscalYear":{"Title":"2017"},"Donor":{"Title":"Bennett Jr and Delphina Dorrance"},"DonorType":{"Title":"Individual"},"Program":{"Title":"Hawaii"},"FieldSite":{"Title":"Other"},"Duration":{"Title":"1"},"FundingStatus":{"Id":3,"Title":"Approved"},"Author":{"Title":"Ashleigh McGovern"},"Editor":{"Title":"Ashleigh McGovern"},"Id":195,"Project":"Conservation course at UHH","TotalCommitment":46972.0,"ProgramCommitment":46972.0,"FieldSiteCommitment":0.0,"Notes":null,"ID":195,"Modified":"2016-12-21T13:40:04Z","Created":"2016-12-21T13:40:04Z"},{"FiscalYear":{"Title":"2017"},"Donor":{"Title":"Joseph and Vera Long Foundation"},"DonorType":{"Title":"Foundation"},"Program":{"Title":"Hawaii"},"FieldSite":{"Title":"Other"},"Duration":{"Title":"1"},"FundingStatus":{"Id":3,"Title":"Approved"},"Author":{"Title":"Ashleigh McGovern"},"Editor":{"Title":"Ashleigh McGovern"},"Id":196,"Project":"Community Conservation in South Kona","TotalCommitment":39989.0,"ProgramCommitment":39989.0,"FieldSiteCommitment":0.0,"Notes":null,"ID":196,"Modified":"2016-12-21T13:42:01Z","Created":"2016-12-21T13:42:01Z"},{"FiscalYear":{"Title":"2017"},"Donor":{"Title":"Julie Wrigley"},"DonorType":{"Title":"Individual"},"Program":{"Title":"Hawaii"},"FieldSite":{"Title":"Other"},"Duration":{"Title":"1"},"FundingStatus":{"Id":3,"Title":"Approved"},"Author":{"Title":"Ashleigh McGovern"},"Editor":{"Title":"Ashleigh McGovern"},"Id":197,"Project":null,"TotalCommitment":10000.0,"ProgramCommitment":10000.0,"FieldSiteCommitment":0.0,"Notes":null,"ID":197,"Modified":"2016-12-21T13:42:33Z","Created":"2016-12-21T13:42:33Z"},{"FiscalYear":{"Title":"2017"},"Donor":{"Title":"Sharon McCormack Living Trust"},"DonorType":{"Title":"Individual"},"Program":{"Title":"Core "},"FieldSite":{"Title":"None"},"Duration":{"Title":"1"},"FundingStatus":{"Id":4,"Title":"Booked"},"Author":{"Title":"Ashleigh McGovern"},"Editor":{"Title":"Ashleigh McGovern"},"Id":198,"Project":"Flexible","TotalCommitment":120000.0,"ProgramCommitment":120000.0,"FieldSiteCommitment":0.0,"Notes":null,"ID":198,"Modified":"2017-03-01T08:16:06Z","Created":"2017-03-01T08:16:06Z"},{"FiscalYear":{"Title":"2017"},"Donor":{"Title":"Geffen Foundation"},"DonorType":{"Title":"Foundation"},"Program":{"Title":"Blue Economies"},"FieldSite":{"Title":"None"},"Duration":{"Title":"2"},"FundingStatus":{"Id":2,"Title":"Submitted"},"Author":{"Title":"Ashleigh McGovern"},"Editor":{"Title":"Ashleigh McGovern"},"Id":199,"Project":"Natural Capital Protocol, Ocean Supplement","TotalCommitment":250000.0,"ProgramCommitment":250000.0,"FieldSiteCommitment":0.0,"Notes":null,"ID":199,"Modified":"2017-04-05T18:40:38Z","Created":"2017-04-05T18:40:38Z"},{"FiscalYear":{"Title":"2017"},"Donor":{"Title":"Heather and Jim Murren"},"DonorType":{"Title":"Individual"},"Program":{"Title":"Aquaculture"},"FieldSite":{"Title":"None"},"Duration":{"Title":"2"},"FundingStatus":{"Id":2,"Title":"Submitted"},"Author":{"Title":"Ashleigh McGovern"},"Editor":{"Title":"Ashleigh McGovern"},"Id":200,"Project":"Best pracitice policy governance","TotalCommitment":80000.0,"ProgramCommitment":80000.0,"FieldSiteCommitment":0.0,"Notes":null,"ID":200,"Modified":"2017-04-05T18:42:53Z","Created":"2017-04-05T18:42:53Z"},{"FiscalYear":{"Title":"2017"},"Donor":{"Title":"Joe + Diane Steinberg"},"DonorType":{"Title":"Individual"},"Program":{"Title":"Core "},"FieldSite":{"Title":"None"},"Duration":{"Title":"5"},"FundingStatus":{"Id":3,"Title":"Approved"},"Author":{"Title":"Ashleigh McGovern"},"Editor":{"Title":"Ashleigh McGovern"},"Id":203,"Project":"Flexible ","TotalCommitment":500000.0,"ProgramCommitment":500000.0,"FieldSiteCommitment":0.0,"Notes":null,"ID":203,"Modified":"2017-04-10T13:00:05Z","Created":"2017-04-10T13:00:05Z"},{"FiscalYear":{"Title":"2017"},"Donor":{"Title":"Joe + Diane Steinberg"},"DonorType":{"Title":"Individual"},"Program":{"Title":"Policy + Governance"},"FieldSite":{"Title":"None"},"Duration":{"Title":"5"},"FundingStatus":{"Id":3,"Title":"Approved"},"Author":{"Title":"Ashleigh McGovern"},"Editor":{"Title":"Ashleigh McGovern"},"Id":204,"Project":"Ocean Health Index","TotalCommitment":1000000.0,"ProgramCommitment":1000000.0,"FieldSiteCommitment":0.0,"Notes":null,"ID":204,"Modified":"2017-04-17T14:47:29Z","Created":"2017-04-10T13:00:57Z"}]}